Workbook

Sheet Instructions
A1: Digital Task Intensity (DTI) — Human Coder Form, NCO-2015 occupations
A2: 3,450 occupations (all NCO-2015 8-digit occupations with descriptions in Vol II). Code each occupation on the "Coding" sheet. Yellow cells are for your answers.
A4: Coder details
B5: Coder name
B6: Coder ID
B7: Date started
B8: Date finished
A10: Rules
A11: 1. | B11: Scale for Q2–Q6: 0 = none · 1 = incidental (occasional, simple) · 2 = regular, basic · 3 = regular, advanced / job-specific · 4 = core (this is the main work).
A12: 2. | B12: Score only from the occupation text; if the text is silent, score 0.
A13: 3. | B13: Q7: for every Q2–Q6 score of 1 or more, copy the exact words from the description into the matching Q7 evidence column. Leave it blank for a score of 0. A missing quote turns the cell orange.
A14: 4. | B14: Q8: give one confidence value (1 low, 2 medium, 3 high) for each of Q2–Q6, in the five Q8 columns.
A15: 5. | B15: Q9 is your overall judgement on 0–10. Do not add up Q2–Q6.
A16: 6. | B16: Q11 is the only question where you use your own knowledge of India today rather than the text.
A17: 7. | B17: Code blind: do not look at LLM scores or other coders' sheets. Do not edit the grey columns.
A18: 8. | B18: The Status column updates itself: Not started → Incomplete → Add evidence → Complete.
A20: Questions
A21: Q | B21: Question | C21: Answer format | D21: Where to enter | E21: Example answer (Accounts Clerk below)
A22: Q1 | B22: Is the description detailed enough to judge digital tasks? | C22: Yes / Partly / No | D22: Q1 column | E22: Yes
A23: Q2 | B23: Basic digital operation: routine use of computers, phones, POS/billing machines, standard software. | C23: 0–4 | D23: Q2 column | E23: 2
A24: Q3 | B24: Digital information processing: searching, recording, managing, analysing digital information. | C24: 0–4 | D24: Q3 column | E24: 3
A25: Q4 | B25: Digital communication & collaboration: e-mail, messaging, video calls, platforms/portals (voice calls do not count). | C25: 0–4 | D25: Q4 column | E25: 2
A26: Q5 | B26: Advanced / specialised digital tools: job-specific software, programming, CAD, GIS, analytics, CNC/PLC systems. | C26: 0–4 | D26: Q5 column | E26: 2
A27: Q6 | B27: Digital problem solving & content creation: creating digital content or solving non-routine problems with digital tools. | C27: 0–4 | D27: Q6 column | E27: 1
A28: Q7 | B28: For each score of 1 or more, which words in the text support it? | C28: Exact words from the text | D28: Five "Q7 evidence" columns | E28: Q2 "accounting software"; Q3 "bank reconciliation statements"; Q4 "by e-mail"; Q5 "accounting software"; Q6 "prepares vouchers, invoices"
A29: Q8 | B29: How confident are you in each of the five scores (Q2–Q6)? | C29: 1 low · 2 medium · 3 high | D29: Five "Q8 confidence" columns | E29: 3, 3, 3, 2, 2
A30: Q9 | B30: Overall, how digital is this occupation? (do not add up Q2–Q6) | C30: 0–10 | D30: Q9 column | E30: 5
A31: Q10 | B31: Is digital work core to the job or a supporting tool? | C31: Core / Supporting / Not relevant | D31: Q10 column | E31: Supporting
A32: Q11 | B32: From your own knowledge: in India today, is this job more digital than the text suggests, the same, or less? | C32: More / Same / Less | D32: Q11 column | E32: More
A33: Q12 | B33: Anything unclear or not fitting the rules? | C33: Short comment (optional) | D33: Q12 column | E33: —
A35: Worked example — Accounts Clerk (illustrative text)
B36: "Records financial transactions in ledgers and accounting software; prepares vouchers, invoices and bank reconciliation statements; maintains digital files of bills and receipts; corresponds with vendors by e-mail regarding payments; prints and files monthly summary reports."
A38: Data source
B39: Occupation titles and descriptions: National Classification of Occupations 2015, Vol II-A and II-B (Ministry of Labour & Employment, DGE). Hierarchy titles and NCO-2004 concordance: NCO-2015 Vol I.
B40: Machine-readable base table: "2015 NCO Draft Data Table" (gilesd-j.com blog, Nov 2025), checked against the official PDFs (median 100% word overlap); 2 duplicate rows removed, 3 missing and 4 cut-off descriptions restored from Vol II.
B41: Reference columns: Group (3-digit) is the level used in PLFS since July 2021. NCO skill level is by division (Div 2 = 4, Div 3 = 3, Div 4–8 = 2, Div 9 = 1; Div 1 not defined). Division 0 (Armed Forces) has no occupation descriptions in Vol II and is not included.

Sheet Coding
A1: OCCUPATION (read only) | E1: Q1 | F1: Q2–Q6 SCORES (0–4) | K1: Q7 EVIDENCE — exact words from the description | P1: Q8 CONFIDENCE (1–3) | U1: Q9–Q12 | Y1: CHECK | Z1: REFERENCE (read only)
A2: Row | B2: NCO-2015 code | C2: Occupation title | D2: Occupation description (NCO-2015 Vol II) | E2: Q1 Detail enough? | F2: Q2 Basic digital operation | G2: Q3 Digital information processing | H2: Q4 Digital communication & collaboration | I2: Q5 Advanced / specialised digital tools | J2: Q6 Digital problem solving & content creation | K2: Q7 evidence for Q2 | L2: Q7 evidence for Q3 | M2: Q7 evidence for Q4 | N2: Q7 evidence for Q5 | O2: Q7 evidence for Q6 | P2: Q8 confidence Q2 | Q2: Q8 confidence Q3 | R2: Q8 confidence Q4 | S2: Q8 confidence Q5 | T2: Q8 confidence Q6 | U2: Q9 Overall (0–10) | V2: Q10 Core / Supporting | W2: Q11 India today vs text | X2: Q12 Comment (optional) | Y2: Status | Z2: Family code (4-digit) | AA2: Family title | AB2: Group code (3-digit, PLFS level) | AC2: Group title | AD2: Division | AE2: Division title | AF2: NCO skill level | AG2: NCO-2004 code | AH2: QP/NOS reference | AI2: NSQF level
A3: 1 | B3: 1111.0100 | C3: Elected Official, Union Government | D3: Elected Official, Union Government serves in various capacities in legislative and executive branches of Union Government. Performs administrative, executive or advisory functions, which include serving as head of the Indian Union; presiding over deliberations of Houses of Parliament; leading council of ministers of Union Government; shaping, determining and defining government policies and directing their application and execution through departmental heads; representing interests of voters in Parliament, on committees and commissions; and taking part in making, amending or repealing laws. Is designated according to work performed or post held, such as: PRESIDENT OF INDIA; RASHTRAPATI. VICE PRESIDENT OF INDIA; UP-RASHTRAPATI. SPEAKER, LOK SABHA. CHAIRMAN, RAJYA SABHA. PRIME MINISTER OF INDIA. MINISTER, UNION GOVERNMENT. MEMBER OF PARLIAMENT. | Y3: =IF(COUNTA(E3:J3,P3:W3)=0,"Not started",IF(COUNTA(E3:J3,P3:W3)<14,"Incomplete",IF((AND(F3<>"",F3&""<>"0",TRIM(K3)="")+AND(G3<>"",G3&""<>"0",TRIM(L3)="")+AND(H3<>"",H3&""<>"0",TRIM(M3)="")+AND(I3<>"",I3&""<>"0",TRIM(N3)="")+AND(J3<>"",J3&""<>"0",TRIM(O3)=""))>0,"Add evidence","Complete"))) | Z3: 1111 | AA3: Legislators | AB3: 111 | AC3: Legislators and Senior Officials | AD3: 1 | AE3: Managers | AF3: Not defined | AG3: 1111.10
A4: 2 | B4: 1111.0200 | C4: Elected Official, State Government | D4: Elected Official, State Government serves in various capacities in legislative and executive branches of State Government. Performs, administrative, executive or advisory functions, which include leading council of ministers of State Government; shaping, determining and defining government policies, and directing application and execution of government policies through departmental heads; presiding over deliberations of Houses of State Legislatures; committees and commissions; and taking part in making, amending or repealing laws. Is designated according to work performed or post held, such as: CHIEF MINISTER. MINISTER, STATE GOVERNMENT. CHAIRMAN, LEGISLATIVE COUNCIL. SPEAKER, LEGISLATIVE ASSEMBLY. MEMBER, LEGISLATIVE ASSEMBLY. | Y4: =IF(COUNTA(E4:J4,P4:W4)=0,"Not started",IF(COUNTA(E4:J4,P4:W4)<14,"Incomplete",IF((AND(F4<>"",F4&""<>"0",TRIM(K4)="")+AND(G4<>"",G4&""<>"0",TRIM(L4)="")+AND(H4<>"",H4&""<>"0",TRIM(M4)="")+AND(I4<>"",I4&""<>"0",TRIM(N4)="")+AND(J4<>"",J4&""<>"0",TRIM(O4)=""))>0,"Add evidence","Complete"))) | Z4: 1111 | AA4: Legislators | AB4: 111 | AC4: Legislators and Senior Officials | AD4: 1 | AE4: Managers | AF4: Not defined | AG4: 1112.10
A5: 3 | B5: 1111.0300 | C5: Elected Official, Local Bodies | D5: Elected Official, Local Bodies serves in various capacities in policy making and executive branches of local bodies. Performs administrative, executive or advisory functions in matters entrusted to local bodies e.g. public health, sanitation, primary education, building and road construction, drainage, street-lighting, raising and collection of admissible local taxes and their proper administration, and all other connected matters for the benefit of local people, including enforcement of local laws and emergency measures as necessary. Is designated according to work performed or post held such as: MAYOR, MUNICIPAL CORPORATION. COUNCILLOR, CITY MUNICIPAL CORPORATION. CHAIRMAN, CITY MUNICIPAL CORPORATION. CHAIRMAN, MUNICIPALITY. MEMBER MUNICIPALITY. CHAIRMAN, DISTRICT BOARD. MEMBER, DISTRICT BOARD. CHAIRMAN, CANTONMENT BOARD. MEMBER, CANTONMENT BOARD. CHAIRMAN, TOWN AREA COMMITTEE. MEMBER, TOWN AREA COMMITTEE. CHAIRMAN, BLOCK SAMITI. SARPANCH, PANCHAYAT. MEMBER, PANCHAYAT. | Y5: =IF(COUNTA(E5:J5,P5:W5)=0,"Not started",IF(COUNTA(E5:J5,P5:W5)<14,"Incomplete",IF((AND(F5<>"",F5&""<>"0",TRIM(K5)="")+AND(G5<>"",G5&""<>"0",TRIM(L5)="")+AND(H5<>"",H5&""<>"0",TRIM(M5)="")+AND(I5<>"",I5&""<>"0",TRIM(N5)="")+AND(J5<>"",J5&""<>"0",TRIM(O5)=""))>0,"Add evidence","Complete"))) | Z5: 1111 | AA5: Legislators | AB5: 111 | AC5: Legislators and Senior Officials | AD5: 1 | AE5: Managers | AF5: Not defined | AG5: 1113.10
A6: 4 | B6: 1111.9900 | C6: Legislators, Other | D6: Elected Officials, Other include all other Elected Officials performing administrative, executive or advisory functions in educational, religious, social, political and community welfare organizations and such other permanent or ad-hoc private bodies, not else-where classified. | Y6: =IF(COUNTA(E6:J6,P6:W6)=0,"Not started",IF(COUNTA(E6:J6,P6:W6)<14,"Incomplete",IF((AND(F6<>"",F6&""<>"0",TRIM(K6)="")+AND(G6<>"",G6&""<>"0",TRIM(L6)="")+AND(H6<>"",H6&""<>"0",TRIM(M6)="")+AND(I6<>"",I6&""<>"0",TRIM(N6)="")+AND(J6<>"",J6&""<>"0",TRIM(O6)=""))>0,"Add evidence","Complete"))) | Z6: 1111 | AA6: Legislators | AB6: 111 | AC6: Legislators and Senior Officials | AD6: 1 | AE6: Managers | AF6: Not defined | AG6: 1119.90
A7: 5 | B7: 1112.0100 | C7: Administrative Official, Union Government | D7: Administrative Official, Union Government serves in various capacities under Union Government. Performs administrative and advisory functions, which include advising minister on all matters of policy and administration within his sphere of responsibility; organizing and directing work of ministries and departments; taking policy decisions to extent authorized; supervising execution and implementation of policies and decisions by field or subordinate offices etc. Is designated according to work performed or post held, such as: MEMBER, OF UNION PUBLIC SERVICE COMMISSION. MEMBER, CENTRAL BOARD OF REVENUE. MEMBER, RAILWAY BOARD. MEMBER PLANNING COMMISSION. SECRETARY TO THE GOVERNMENT OF INDIA JOINT SECRETARY TO THE GOVERNMENT OF INDIA. DEPUTY SECRETARY TO THE GOVERNMENT OF INDIA. UNDER SECRETARY TO THE GOVERNMENT OF INDIA. DIRECTOR-GENERAL, CIVIL AVIATION. DIRECTOR GENERAL, ALL INDIA RADIO DIRECTOR-GENERAL, POSTS AND TELEGRAPHS. DIRECTOR-GENERAL, SUPPLIES AND DISPOSALS. DIRECTOR-GENERAL SHIPPING. DIRECTOR-GENERAL OF EMPLOYMENT AND TRAINING. CONTROLLER AND AUDITOR GENERAL. CONTROLLER, IRON AND STEEL. COMMISSIONER, TEXTILE. CUSTODIAN GENERAL. CHIEF CONTROLLER OF IMPORTS AND EXPORTS. CHIEF COMMISSIONER, ELECTION. CHIEF COMMISSIONER, LABOUR COMMISSIONER, SALT. REGISTRAR-GENERAL, CENSUS | Y7: =IF(COUNTA(E7:J7,P7:W7)=0,"Not started",IF(COUNTA(E7:J7,P7:W7)<14,"Incomplete",IF((AND(F7<>"",F7&""<>"0",TRIM(K7)="")+AND(G7<>"",G7&""<>"0",TRIM(L7)="")+AND(H7<>"",H7&""<>"0",TRIM(M7)="")+AND(I7<>"",I7&""<>"0",TRIM(N7)="")+AND(J7<>"",J7&""<>"0",TRIM(O7)=""))>0,"Add evidence","Complete"))) | Z7: 1112 | AA7: Senior Government Officials | AB7: 111 | AC7: Legislators and Senior Officials | AD7: 1 | AE7: Managers | AF7: Not defined | AG7: 1121.10
A8: 6 | B8: 1112.0200 | C8: Diplomat | D8: Diplomat represents Union of India in other countries or at international organizations, meetings and conferences. Interprets policies of Indian Government in foreign countries and advises his Government on matters of foreign relations, trade, commerce, etc. Negotiates and enters into agreements with other countries and nations. Issues visas to foreigners for visit to India and looks after welfare of Indians abroad, and generally promotes interest of his country. Is designated according to rank held or work performed, such as: AMBASSADOR HIGH COMMISSIONER ENVOY MINISTER (DIPLOMAT) PERMANENT REPRESENTATIVE COUNSEL GENERAL CHARGE D AFFAIRS TRADE COMMISSIONER. | Y8: =IF(COUNTA(E8:J8,P8:W8)=0,"Not started",IF(COUNTA(E8:J8,P8:W8)<14,"Incomplete",IF((AND(F8<>"",F8&""<>"0",TRIM(K8)="")+AND(G8<>"",G8&""<>"0",TRIM(L8)="")+AND(H8<>"",H8&""<>"0",TRIM(M8)="")+AND(I8<>"",I8&""<>"0",TRIM(N8)="")+AND(J8<>"",J8&""<>"0",TRIM(O8)=""))>0,"Add evidence","Complete"))) | Z8: 1112 | AA8: Senior Government Officials | AB8: 111 | AC8: Legislators and Senior Officials | AD8: 1 | AE8: Managers | AF8: Not defined | AG8: 1121.20
A9: 7 | B9: 1112.0300 | C9: Executive Officials, Union Government | D9: Executive Official, Union Government serves in various executive capacities in Union Government, giving effect to policies and decisions of Government. Performs or supervises performance of other executives and field duties such as assessing and collecting revenues; issuing passports, licenses and other authorizations; supervising elections; reconciling parties in trade disputes; inspecting offices and establishments; enforcing and implementing various rules, regulations and provisions of law. Is designated according to work performed or post held, such as: COMMISSIONER, DEVELOPMENT COMMISSIONER, INCOME-TAX CUSTODIAN, EVACUEE PROPERTY DIRECTOR OF INSPECTION, CUSTOMS DIRECTOR, MARKETING DIRECTOR OF TRAINING, DIRECTOR OF EMPLOYMENT EXCHANGES, REGIONAL LABOUR COMMISSIONER, COLLECTOR, CENTRAL EXCISE, SUPERINTENDENT, CUSTOMS, INCOME-TAX OFFICER, SUPERINTENDENT, CENTRAL EXCISE, PASSPORT OFFICER, SETTLEMENT OFFICER, CONCILIATION OFFICER (CENTRAL). | Y9: =IF(COUNTA(E9:J9,P9:W9)=0,"Not started",IF(COUNTA(E9:J9,P9:W9)<14,"Incomplete",IF((AND(F9<>"",F9&""<>"0",TRIM(K9)="")+AND(G9<>"",G9&""<>"0",TRIM(L9)="")+AND(H9<>"",H9&""<>"0",TRIM(M9)="")+AND(I9<>"",I9&""<>"0",TRIM(N9)="")+AND(J9<>"",J9&""<>"0",TRIM(O9)=""))>0,"Add evidence","Complete"))) | Z9: 1112 | AA9: Senior Government Officials | AB9: 111 | AC9: Legislators and Senior Officials | AD9: 1 | AE9: Managers | AF9: Not defined | AG9: 1121.30
A10: 8 | B10: 1112.0400 | C10: Administrative Official, State Government | D10: Administrative Official, State Government serves in various capacities in State Government. Performs administrative and advisory functions which include serving as Head of State; advising ministers, on all matters of policy and administration within his sphere of responsibility; organizing and directing work of departments; taking policy decisions to the extent authorised; supervising execution and implementation of policies and decisions by field or subordinate officers. Is designated according to work performed or post held, such as: GOVERNOR; RAJYAPAL; LIEUTENANT GOVERNOR MEMBER, STATE PUBLIC SERVICE COMMISSION, MEMBER, BOARD OF REVENUE, CHIEF SECRETARY TO GOVERNMENT (STATE), SECRETARY TO GOVERNMENT (STATE), DEPUTY SECRETARY TO GOVERNMENT (STATE), UNDER SECRETARY TO GOVERNMENT (STATE), CHIEF COMMISSIONER DEVELOPMENT, COMMISSIONER OF DIVISION, DIRECTOR OF EDUCATION, DIRECTOR OF INDUSTRIES. | Y10: =IF(COUNTA(E10:J10,P10:W10)=0,"Not started",IF(COUNTA(E10:J10,P10:W10)<14,"Incomplete",IF((AND(F10<>"",F10&""<>"0",TRIM(K10)="")+AND(G10<>"",G10&""<>"0",TRIM(L10)="")+AND(H10<>"",H10&""<>"0",TRIM(M10)="")+AND(I10<>"",I10&""<>"0",TRIM(N10)="")+AND(J10<>"",J10&""<>"0",TRIM(O10)=""))>0,"Add evidence","Complete"))) | Z10: 1112 | AA10: Senior Government Officials | AB10: 111 | AC10: Legislators and Senior Officials | AD10: 1 | AE10: Managers | AF10: Not defined | AG10: 1122.10
A11: 9 | B11: 1112.0500 | C11: Executive Official, State Government | D11: Executive Official, State Government serves in various capacities in State Government giving effect to policies and decisions of Government. Performs or supervises performance of executive and field duties which include maintenance of law and order; assessing and collecting taxes, duties, land revenues, etc.; issuing licenses; executing development schemes; reconciling parties in trade disputes; inspecting schools, factories, shops, offices and establishments; and enforcing various rules, regulations and provisions of law. Is designated according to work performed or post held, such as: COLLECTOR; DEPUTY COLLECTOR; SUB-DEPUTY COLLECTOR; DEPUTY COMMISSIONER. DISTRICT OFFICER; SUB-DIVISIONAL OFFICER; LAND RECORD OFFICER; TEHSILDAR; SUPERINTENDENT OF POLICE CIRCLE OFFICE; SALES-TAX OFFICER; SUPERINTENDENT, JAIL; JAILOR, SUPERINTENDENT OF INDUSTRIES DISTRICT INDUSTRIES OFFICER MARKETING OFFICER. RATIONING OFFICER. SUPPLY OFFICER. RENT CONTROL AND EVICTION OFFICER, REGIONAL TRANSPORT OFFICER, DISTRICT PLANNING OFFICER, CO-OPERATIVE OFFICER, CONCILIATION OFFICER (STATE), PANCHAYAT RAJ OFFICER. | Y11: =IF(COUNTA(E11:J11,P11:W11)=0,"Not started",IF(COUNTA(E11:J11,P11:W11)<14,"Incomplete",IF((AND(F11<>"",F11&""<>"0",TRIM(K11)="")+AND(G11<>"",G11&""<>"0",TRIM(L11)="")+AND(H11<>"",H11&""<>"0",TRIM(M11)="")+AND(I11<>"",I11&""<>"0",TRIM(N11)="")+AND(J11<>"",J11&""<>"0",TRIM(O11)=""))>0,"Add evidence","Complete"))) | Z11: 1112 | AA11: Senior Government Officials | AB11: 111 | AC11: Legislators and Senior Officials | AD11: 1 | AE11: Managers | AF11: Not defined | AG11: 1122.20
A12: 10 | B12: 1112.0600 | C12: Administrative and Executive Officials, Quasi Government (Central) | D12: Administrative and Executive Official, Quasi Government (Central) plans, organizes, co-ordinates and controls within authority delegated, activities of quasi-government organizations, establishment, etc. or one or more of its departments/branches or sections; and includes officials such as: CHAIRMAN, UNIVERSITY GRANTS COMMISSION CHAIRMAN, COAL MINES WELFARE COMMISSION, SECRETARY, INDIAN RED CROSS SOCIETY, SECRETARY, MICA MINES LABOUR WELFARE FUND ADVISORY COMMITTEE, SECRETARY, RAILWAY RATES TRIBUNAL, CONTROLLER OF EMIGRANT LABOUR, DIRECTOR-GENERAL, EMPLOYEES STATE INSURANCE CORPORATION. | Y12: =IF(COUNTA(E12:J12,P12:W12)=0,"Not started",IF(COUNTA(E12:J12,P12:W12)<14,"Incomplete",IF((AND(F12<>"",F12&""<>"0",TRIM(K12)="")+AND(G12<>"",G12&""<>"0",TRIM(L12)="")+AND(H12<>"",H12&""<>"0",TRIM(M12)="")+AND(I12<>"",I12&""<>"0",TRIM(N12)="")+AND(J12<>"",J12&""<>"0",TRIM(O12)=""))>0,"Add evidence","Complete"))) | Z12: 1112 | AA12: Senior Government Officials | AB12: 111 | AC12: Legislators and Senior Officials | AD12: 1 | AE12: Managers | AF12: Not defined | AG12: 1123.10
A13: 11 | B13: 1112.0700 | C13: Administrative & Executive Officials, Quasi Government (State) | D13: Administrative and Executive Official, Quasi Government (State) plans, organizes, co-ordinates and controls within authority delegated, activities of quasi-government organizations, establishments, etc. or one or more of its departments/branches or sections; and includes officials such as: VICE CHANCELLOR, STATE UNIVERSITIES, DEAN, STATE AUTONOMOUS EDUCATIONAL INSTITUTES, CHAIRMAN, STATE CORPORATIONS/BOARDS, CHAIRMAN, HARYANA URBAN DEVELOPMENT AUTHORITY, SECRETARY, GHAZIABAD DEVELOPMENT AUTHORITY. | Y13: =IF(COUNTA(E13:J13,P13:W13)=0,"Not started",IF(COUNTA(E13:J13,P13:W13)<14,"Incomplete",IF((AND(F13<>"",F13&""<>"0",TRIM(K13)="")+AND(G13<>"",G13&""<>"0",TRIM(L13)="")+AND(H13<>"",H13&""<>"0",TRIM(M13)="")+AND(I13<>"",I13&""<>"0",TRIM(N13)="")+AND(J13<>"",J13&""<>"0",TRIM(O13)=""))>0,"Add evidence","Complete"))) | Z13: 1112 | AA13: Senior Government Officials | AB13: 111 | AC13: Legislators and Senior Officials | AD13: 1 | AE13: Managers | AF13: Not defined | AG13: 1123.20
A14: 12 | B14: 1112.0800 | C14: Administrative and Executive Officials, Local Bodies | D14: Administrative and Executive Official, Local Bodies plans, organizes, co-ordinates and controls functions of the city corporation, improvement trust, municipality, district board, cantonment board, notified area committee or other local bodies, and executes and implements or supervises execution and implementation of decisions, rules and regulations and by-laws of local bodies and also assesses and collects local taxes. Is designated according to work performed or post held, such as: COMMISSIONER, CITY CORPORATION, EXECUTIVE OFFICER, IMPROVEMENT TRUST; EXECUTIVE OFFICER, CANTONMENT, BOARD; EXECUTIVE OFFICER; MUNICIPAL BOARD, SECRETARY, DISTRICT BOARD TAX SUPERINTENDENT, OCTROI SUPERINTENDENT | Y14: =IF(COUNTA(E14:J14,P14:W14)=0,"Not started",IF(COUNTA(E14:J14,P14:W14)<14,"Incomplete",IF((AND(F14<>"",F14&""<>"0",TRIM(K14)="")+AND(G14<>"",G14&""<>"0",TRIM(L14)="")+AND(H14<>"",H14&""<>"0",TRIM(M14)="")+AND(I14<>"",I14&""<>"0",TRIM(N14)="")+AND(J14<>"",J14&""<>"0",TRIM(O14)=""))>0,"Add evidence","Complete"))) | Z14: 1112 | AA14: Senior Government Officials | AB14: 111 | AC14: Legislators and Senior Officials | AD14: 1 | AE14: Managers | AF14: Not defined | AG14: 1124.10
... A37: 35 | B37: 1120.1800 | C37: Director Manufacturing | D37: Director, Manufacturing plans, organizes, co-ordinates and controls within authority delegated, activities of private or public organizations, or one or more of its departments or branches, engaged in producing, maintaining or repairing capital or consumer goods, excluding crops, minerals, electricity and natural gas. Is designated according to work performed, authority exercised or economic activity directed such as: MANAGING DIRECTOR, (MANUFACTURING). DIRECTOR, PRODUCTION(MANUFACTURING). DIRECTOR, WORKS(MANUFACTURING). DIRECTOR, STEEL PLANT. DIRECTOR, TANNERY. DIRECTOR, BAKERY. DIRECTOR, SADDLERY. | Y37: =IF(COUNTA(E37:J37,P37:W37)=0,"Not started",IF(COUNTA(E37:J37,P37:W37)<14,"Incomplete",IF((AND(F37<>"",F37&""<>"0",TRIM(K37)="")+AND(G37<>"",G37&""<>"0",TRIM(L37)="")+AND(H37<>"",H37&""<>"0",TRIM(M37)="")+AND(I37<>"",I37&""<>"0",TRIM(N37)="")+AND(J37<>"",J37&""<>"0",TRIM(O37)=""))>0,"Add evidence","Complete"))) | Z37: 1120 | AA37: Managing Directors and Chief Executives | AB37: 112 | AC37: Managing Directors and Chief Executives | AD37: 1 | AE37: Managers | AF37: Not defined | AG37: 1214.20
A38: 36 | B38: 1120.1900 | C38: Working Proprietor, Wholesale Trade/Proprietor, Wholesale Trade | D38: Working Proprietor, Wholesale Trade purchases goods in bulk and sells them to retailers or other large consumers for profit. Lays down and controls business policies to ensure profits, keeping in view price line, market trend and demand and supply position. Appoints Directors, Managers and Representatives and delegates financial and operational powers to them, if necessary. Runs wholesale trade on monopoly or zonal basis in specific commodities either by importing them from outside or manufacturing them in his own or other concern. May require a licence or permit from public authorities for wholesale trade. May undertake export business. | Y38: =IF(COUNTA(E38:J38,P38:W38)=0,"Not started",IF(COUNTA(E38:J38,P38:W38)<14,"Incomplete",IF((AND(F38<>"",F38&""<>"0",TRIM(K38)="")+AND(G38<>"",G38&""<>"0",TRIM(L38)="")+AND(H38<>"",H38&""<>"0",TRIM(M38)="")+AND(I38<>"",I38&""<>"0",TRIM(N38)="")+AND(J38<>"",J38&""<>"0",TRIM(O38)=""))>0,"Add evidence","Complete"))) | Z38: 1120 | AA38: Managing Directors and Chief Executives | AB38: 112 | AC38: Managing Directors and Chief Executives | AD38: 1 | AE38: Managers | AF38: Not defined
A39: 37 | B39: 1120.2000 | C39: Working Proprietor, Retail Trade/Proprietor, Retail Trade | D39: Working Proprietor, Retail Trade conducts business in retail trade on own account, buying merchandise from manufacturers or wholesalers according to public demand and sells them to customers for profit. Lays down business policies regarding margin of profit and compliance with prescribed rules and regulations. May appoint Directors and Managers and may delegate financial and operational powers to them. May obtain licence or permit from public authorities for retail trade. | Y39: =IF(COUNTA(E39:J39,P39:W39)=0,"Not started",IF(COUNTA(E39:J39,P39:W39)<14,"Incomplete",IF((AND(F39<>"",F39&""<>"0",TRIM(K39)="")+AND(G39<>"",G39&""<>"0",TRIM(L39)="")+AND(H39<>"",H39&""<>"0",TRIM(M39)="")+AND(I39<>"",I39&""<>"0",TRIM(N39)="")+AND(J39<>"",J39&""<>"0",TRIM(O39)=""))>0,"Add evidence","Complete"))) | Z39: 1120 | AA39: Managing Directors and Chief Executives | AB39: 112 | AC39: Managing Directors and Chief Executives | AD39: 1 | AE39: Managers | AF39: Not defined | AG39: 1214.40
A40: 38 | B40: 1120.2100 | C40: Director, Wholesale Trade | D40: Director, Wholesale Trade lays down policies within powers ,delegated, and plans, controls and directs operation of private or public enterprise or segment of its activities engaged in buying and selling of goods in wholesale. Is designated according to work performed, such as: MANAGING DIRECTOR (Wholesale Trade). CHAIRMAN, BOARD OF DIRECTORS (Wholesale Trade). | Y40: =IF(COUNTA(E40:J40,P40:W40)=0,"Not started",IF(COUNTA(E40:J40,P40:W40)<14,"Incomplete",IF((AND(F40<>"",F40&""<>"0",TRIM(K40)="")+AND(G40<>"",G40&""<>"0",TRIM(L40)="")+AND(H40<>"",H40&""<>"0",TRIM(M40)="")+AND(I40<>"",I40&""<>"0",TRIM(N40)="")+AND(J40<>"",J40&""<>"0",TRIM(O40)=""))>0,"Add evidence","Complete"))) | Z40: 1120 | AA40: Managing Directors and Chief Executives | AB40: 112 | AC40: Managing Directors and Chief Executives | AD40: 1 | AE40: Managers | AF40: Not defined | AG40: 1214.50
A41: 39 | B41: 1120.2200 | C41: Director, Retail Trade | D41: Director, Retail Trade lays down policies within powers delegated and plans, controls and directs operation of private or public enterprises or a segment of its activities, engaged in buying and selling goods in retail. Is designated according to work performed such as: MANAGING DIRECTOR (Retail Trade), CHAIRMAN, BOARD OF DIRECTORS (Retail Trade) DIRECTOR-IN-CHARGE (Retail Trade). | Y41: =IF(COUNTA(E41:J41,P41:W41)=0,"Not started",IF(COUNTA(E41:J41,P41:W41)<14,"Incomplete",IF((AND(F41<>"",F41&""<>"0",TRIM(K41)="")+AND(G41<>"",G41&""<>"0",TRIM(L41)="")+AND(H41<>"",H41&""<>"0",TRIM(M41)="")+AND(I41<>"",I41&""<>"0",TRIM(N41)="")+AND(J41<>"",J41&""<>"0",TRIM(O41)=""))>0,"Add evidence","Complete"))) | Z41: 1120 | AA41: Managing Directors and Chief Executives | AB41: 112 | AC41: Managing Directors and Chief Executives | AD41: 1 | AE41: Managers | AF41: Not defined | AG41: 1214.60
A42: 40 | B42: 1120.2300 | C42: Working Proprietor, Transport | D42: Working Proprietor, Transport plans, organizes, co-ordinates and controls activities of the organization or establishment wholly or partly owned by him, is engaged in transporting passengers and freight by buses, trucks, taxis, rickshaws, tongas, and other means of road transport; by boats, launches, ships, etc. plying on inland or coastal waters or on high seas; by aircraft for providing transport and other services, incidental to transport. | Y42: =IF(COUNTA(E42:J42,P42:W42)=0,"Not started",IF(COUNTA(E42:J42,P42:W42)<14,"Incomplete",IF((AND(F42<>"",F42&""<>"0",TRIM(K42)="")+AND(G42<>"",G42&""<>"0",TRIM(L42)="")+AND(H42<>"",H42&""<>"0",TRIM(M42)="")+AND(I42<>"",I42&""<>"0",TRIM(N42)="")+AND(J42<>"",J42&""<>"0",TRIM(O42)=""))>0,"Add evidence","Complete"))) | Z42: 1120 | AA42: Managing Directors and Chief Executives | AB42: 112 | AC42: Managing Directors and Chief Executives | AD42: 1 | AE42: Managers | AF42: Not defined | AG42: 1215.10
A43: 41 | B43: 1120.2400 | C43: Director, Transport | D43: Director, Transport plans organizes, co-ordinates and controls, within authority delegated, activities of private or public organizations or one or more of its departments, branches or sections, engaged in transporting passengers and freight by railways, tramways, buses, trucks, taxis, rickshaws, animal transport and other means of road transport; by boats, launches and ships plying on rivers, coastal waters, and high seas; by aircrafts; and operating services incidental to transport. Is designated according to work performed, powers exercised of service controlled, such as: MANAGING DIRECTOR (TRANSPORT). DIRECTOR, TRAFFIC GENERAL, MANAGER, RAILWAYS, DIRECTOR, ROADWAYS, CHIEF OPERATING SUPERINTENDENT(RAILWAYS). CHIEF COMMERCIAL SUPERINTENDENT(RAILWAYS). | Y43: =IF(COUNTA(E43:J43,P43:W43)=0,"Not started",IF(COUNTA(E43:J43,P43:W43)<14,"Incomplete",IF((AND(F43<>"",F43&""<>"0",TRIM(K43)="")+AND(G43<>"",G43&""<>"0",TRIM(L43)="")+AND(H43<>"",H43&""<>"0",TRIM(M43)="")+AND(I43<>"",I43&""<>"0",TRIM(N43)="")+AND(J43<>"",J43&""<>"0",TRIM(O43)=""))>0,"Add evidence","Complete"))) | Z43: 1120 | AA43: Managing Directors and Chief Executives | AB43: 112 | AC43: Managing Directors and Chief Executives | AD43: 1 | AE43: Managers | AF43: Not defined | AG43: 1215.20
A44: 42 | B44: 1120.2500 | C44: Director, Communication | D44: Director, Communication plans, organizes, co-ordinates and controls, within authority delegated, activities of public or private organization or one or more of its departments or branches, engaged in providing postal, telephone, telegraph, wireless and other communication services. Is designated according to powers exercised or type of communication service directed such as: DIRECTOR, POSTAL SERVICES, POST MASTER GENERAL. DIRECTOR, OVERSEAS COMMUNICATION SERVICES. DIRECTOR OF TELEPHONES, DIRECTOR OF RAILWAY MAIL SERVICE. | Y44: =IF(COUNTA(E44:J44,P44:W44)=0,"Not started",IF(COUNTA(E44:J44,P44:W44)<14,"Incomplete",IF((AND(F44<>"",F44&""<>"0",TRIM(K44)="")+AND(G44<>"",G44&""<>"0",TRIM(L44)="")+AND(H44<>"",H44&""<>"0",TRIM(M44)="")+AND(I44<>"",I44&""<>"0",TRIM(N44)="")+AND(J44<>"",J44&""<>"0",TRIM(O44)=""))>0,"Add evidence","Complete"))) | Z44: 1120 | AA44: Managing Directors and Chief Executives | AB44: 112 | AC44: Managing Directors and Chief Executives | AD44: 1 | AE44: Managers | AF44: Not defined | AG44: 1215.30
A45: 43 | B45: 1120.2600 | C45: Director, Airport | D45: Director, Airport plans, directs, and co-ordinates, through subordinate personnel, activities concerned with construction and maintenance of airport facilities and operation of airport in accordance with governmental agencies or commission policies and regulations. Consults with commission members, governmental officials, or representatives of airlines to discuss and plan matters, such as design and development of airport facilities, formulation of operating rules, regulations, and procedures, and aircraft landing, taxiing, and take-off patterns for various types of aircrafts. Negotiates with representatives of airlines, utility companies, or individuals for acquisition of property for development of airports, lease of airport buildings and facilities, or use of rights-of-way over private property. Formulates procedures for use in event of aircraft accidents, fires, or other emergencies. Inspects airport facilities, such as runways, buildings, beacons and lighting, and automotive or construction equipment, or reviews inspection reports, to determine repairs, replacement, or improvements required. Co-ordinates activities of personnel involved in repair and maintenance of airport facilities, buildings, and equipment to minimize interruption of airport operations and improve efficiency. Directs personnel in investigating violations of aerial or ground traffic regulations, reviews investigation reports, and initiates actions to be taken against violators. Directs studies on noise abatement resulting from complaints of excessive noise from low flying aircraft or other operations. Reviews reports of expenditures for previous fiscal year, proposes improvements to facilitate, estimated increase in volume of traffic, in order to prepare budget estimates for upcoming fiscal year. Represents airport before civic or other organizational groups, courts, boards, and commissions. | Y45: =IF(COUNTA(E45:J45,P45:W45)=0,"Not started",IF(COUNTA(E45:J45,P45:W45)<14,"Incomplete",IF((AND(F45<>"",F45&""<>"0",TRIM(K45)="")+AND(G45<>"",G45&""<>"0",TRIM(L45)="")+AND(H45<>"",H45&""<>"0",TRIM(M45)="")+AND(I45<>"",I45&""<>"0",TRIM(N45)="")+AND(J45<>"",J45&""<>"0",TRIM(O45)=""))>0,"Add evidence","Complete"))) | Z45: 1120 | AA45: Managing Directors and Chief Executives | AB45: 112 | AC45: Managing Directors and Chief Executives | AD45: 1 | AE45: Managers | AF45: Not defined | AG45: 1215.40
A46: 44 | B46: 1120.2700 | C46: Working Proprietor, Storage and Warehousing | D46: Working Proprietor, Storage and Warehousing plans and organizes storage warehousing and freight handling services to public and private organizations by land, sea or air and arranges allied transport and communication facilities to parties concerned. Obtains license from Government where necessary, and lays down business policies. Appoints Directors, Agents and Managers and delegates required financial and other powers to them to ensure smooth running of business, desired margin of profit and compliance with business terms and Government rules and regulations. | Y46: =IF(COUNTA(E46:J46,P46:W46)=0,"Not started",IF(COUNTA(E46:J46,P46:W46)<14,"Incomplete",IF((AND(F46<>"",F46&""<>"0",TRIM(K46)="")+AND(G46<>"",G46&""<>"0",TRIM(L46)="")+AND(H46<>"",H46&""<>"0",TRIM(M46)="")+AND(I46<>"",I46&""<>"0",TRIM(N46)="")+AND(J46<>"",J46&""<>"0",TRIM(O46)=""))>0,"Add evidence","Complete"))) | Z46: 1120 | AA46: Managing Directors and Chief Executives | AB46: 112 | AC46: Managing Directors and Chief Executives | AD46: 1 | AE46: Managers | AF46: Not defined | AG46: 1216.10
A47: 45 | B47: 1120.2800 | C47: Director, Storage and Warehousing | D47: Director, Storage and Warehousing plans, organizes, co-ordinates and controls, within authority delegated, activities of public or private organizations, or one or more of its branches, engaged in providing storage and warehouse facilities on prescribed terms and conditions to Government and private parties. May arrange facilities of transport and communication as required. May specialize in any particular type of item or commodity such as machinery and engineering items, explosives, perishable goods, etc. and be designated accordingly. | Y47: =IF(COUNTA(E47:J47,P47:W47)=0,"Not started",IF(COUNTA(E47:J47,P47:W47)<14,"Incomplete",IF((AND(F47<>"",F47&""<>"0",TRIM(K47)="")+AND(G47<>"",G47&""<>"0",TRIM(L47)="")+AND(H47<>"",H47&""<>"0",TRIM(M47)="")+AND(I47<>"",I47&""<>"0",TRIM(N47)="")+AND(J47<>"",J47&""<>"0",TRIM(O47)=""))>0,"Add evidence","Complete"))) | Z47: 1120 | AA47: Managing Directors and Chief Executives | AB47: 112 | AC47: Managing Directors and Chief Executives | AD47: 1 | AE47: Managers | AF47: Not defined | AG47: 1216.20
A48: 46 | B48: 1120.2900 | C48: Working Proprietor, Lodging and Catering Services | D48: Working Proprietor, Lodging and Catering Services plans, organizes, co-ordinates and controls operations of the organization or establishment wholly or partly owned by him and is engaged in serving food, drinks and beverages and providing lodging and camping facilities to public. Included are: WORKING PROPRIETOR, HOTEL. WORKING PROPRIETOR, RESTAURANT. WORKING PROPRIETOR, CAFE WORKING PROPRIETOR, COFFEE HOUSE. | Y48: =IF(COUNTA(E48:J48,P48:W48)=0,"Not started",IF(COUNTA(E48:J48,P48:W48)<14,"Incomplete",IF((AND(F48<>"",F48&""<>"0",TRIM(K48)="")+AND(G48<>"",G48&""<>"0",TRIM(L48)="")+AND(H48<>"",H48&""<>"0",TRIM(M48)="")+AND(I48<>"",I48&""<>"0",TRIM(N48)="")+AND(J48<>"",J48&""<>"0",TRIM(O48)=""))>0,"Add evidence","Complete"))) | Z48: 1120 | AA48: Managing Directors and Chief Executives | AB48: 112 | AC48: Managing Directors and Chief Executives | AD48: 1 | AE48: Managers | AF48: Not defined | AG48: 1217.10
A49: 47 | B49: 1120.3000 | C49: Director, Lodging and Catering Services/Director Food and Beverage Service | D49: Director, Lodging and Catering Services plans, organizes and controls, within authority delegated, activities of public or private organizations or establishments or one or more of its branches, engaged in preparing and serving food, drinks and beverages and providing lodging, and camping facilities to public. Included are: DIRECTOR, HOTEL. DIRECTOR, RESTAURANT. DIRECTOR, COFFEE HOUSE | Y49: =IF(COUNTA(E49:J49,P49:W49)=0,"Not started",IF(COUNTA(E49:J49,P49:W49)<14,"Incomplete",IF((AND(F49<>"",F49&""<>"0",TRIM(K49)="")+AND(G49<>"",G49&""<>"0",TRIM(L49)="")+AND(H49<>"",H49&""<>"0",TRIM(M49)="")+AND(I49<>"",I49&""<>"0",TRIM(N49)="")+AND(J49<>"",J49&""<>"0",TRIM(O49)=""))>0,"Add evidence","Complete"))) | Z49: 1120 | AA49: Managing Directors and Chief Executives | AB49: 112 | AC49: Managing Directors and Chief Executives | AD49: 1 | AE49: Managers | AF49: Not defined | AG49: 1217.20
A50: 48 | B50: 1120.3100 | C50: Executive Chef | D50: Executive Chef co-ordinates activities and directs indoctrination and training of CHEFS, COOKS; and other kitchen workers engaged in preparing and cooking food in hotels or restaurants to ensure an efficient and profitable food service. Plans or participates in planning menus and utilisation of food surpluses and leftovers, taking into account probable number of guests, marketing conditions, popularity of various dishes, and decency of menu. Estimates food consumption and purchase or requisition of foodstuff and kitchen supplies. Reviews menus, analyses recipes, determines food, labour, and overhead costs, and assigns price to menu items. Directs food apportionment policy to control costs. Supervises cooking and other kitchen personnel and co-ordinates their assignments to ensure economical and timely food production. Observes methods of food preparation and cooking, size of portions, and garnishing of food to ensure food is prepared in prescribed manner. Tests cooked food by tasting and smelling them. Devises special dishes and develops recipes. Hires and discharges employees. Familiarizes newly hired CHEFS and COOKS with practices of the restaurant kitchen and oversees training of COOK APPRENTICES. Maintains time and payroll records. Establishes and enforces nutrition and sanitation standards for the restaurant. May supervise or co-operate with STEWARD/STEWARDESS in matters pertaining to kitchen, pantry, and storeroom. | Y50: =IF(COUNTA(E50:J50,P50:W50)=0,"Not started",IF(COUNTA(E50:J50,P50:W50)<14,"Incomplete",IF((AND(F50<>"",F50&""<>"0",TRIM(K50)="")+AND(G50<>"",G50&""<>"0",TRIM(L50)="")+AND(H50<>"",H50&""<>"0",TRIM(M50)="")+AND(I50<>"",I50&""<>"0",TRIM(N50)="")+AND(J50<>"",J50&""<>"0",TRIM(O50)=""))>0,"Add evidence","Complete"))) | Z50: 1120 | AA50: Managing Directors and Chief Executives | AB50: 112 | AC50: Managing Directors and Chief Executives | AD50: 1 | AE50: Managers | AF50: Not defined | AG50: 1217.30
... A53: 51 | B53: 1120.3400 | C53: Station Director, Radio/TV | D53: Station Director, Radio/TV directs and co-ordinates activities of radio or television station, or of cable television franchise. Supervises directly, or through subordinates, personnel engaged in departments, such as sales, programme or engineering. Observes activities to ensure compliance with government regulations. Discusses plans with the marketing personnel to promote sales of programmes and time periods to advertisers and their agencies. Confers with owners or company senior management to discuss station policies and administrative procedures. May prepare operational budget and monitor expenses for station or franchise. May negotiate with motion picture companies for purchase of independent film programmes. May negotiate cable franchise contract with local issuing authority. May develop strategies to promote sales of new cable television service or upgraded service to customers within the franchise area. May contact prospective buyers of station time to promote sale of station services. May manage stations engaged in transmitting broadcasts to foreign countries and be known as Director, International Broadcasting (radio-television broadcast). May perform different duties and responsibilities, according to station size and network affiliation. | Y53: =IF(COUNTA(E53:J53,P53:W53)=0,"Not started",IF(COUNTA(E53:J53,P53:W53)<14,"Incomplete",IF((AND(F53<>"",F53&""<>"0",TRIM(K53)="")+AND(G53<>"",G53&""<>"0",TRIM(L53)="")+AND(H53<>"",H53&""<>"0",TRIM(M53)="")+AND(I53<>"",I53&""<>"0",TRIM(N53)="")+AND(J53<>"",J53&""<>"0",TRIM(O53)=""))>0,"Add evidence","Complete"))) | Z53: 1120 | AA53: Managing Directors and Chief Executives | AB53: 112 | AC53: Managing Directors and Chief Executives | AD53: 1 | AE53: Managers | AF53: Not defined | AG53: 1218.30
A54: 52 | B54: 1120.3401 | C54: Account Director (Advertising Agency) | D54: Account Director (Advertising Agency) is responsible for managing the clients’ advertisement portfolio. | Y54: =IF(COUNTA(E54:J54,P54:W54)=0,"Not started",IF(COUNTA(E54:J54,P54:W54)<14,"Incomplete",IF((AND(F54<>"",F54&""<>"0",TRIM(K54)="")+AND(G54<>"",G54&""<>"0",TRIM(L54)="")+AND(H54<>"",H54&""<>"0",TRIM(M54)="")+AND(I54<>"",I54&""<>"0",TRIM(N54)="")+AND(J54<>"",J54&""<>"0",TRIM(O54)=""))>0,"Add evidence","Complete"))) | Z54: 1120 | AA54: Managing Directors and Chief Executives | AB54: 112 | AC54: Managing Directors and Chief Executives | AD54: 1 | AE54: Managers | AF54: Not defined | AH54: MES/Q0207
A55: 53 | B55: 1120.3402 | C55: Sales Director (Media Org) | D55: Sales Director (Media Org) is responsible for leading the sales efforts of a media and entertainment company. | Y55: =IF(COUNTA(E55:J55,P55:W55)=0,"Not started",IF(COUNTA(E55:J55,P55:W55)<14,"Incomplete",IF((AND(F55<>"",F55&""<>"0",TRIM(K55)="")+AND(G55<>"",G55&""<>"0",TRIM(L55)="")+AND(H55<>"",H55&""<>"0",TRIM(M55)="")+AND(I55<>"",I55&""<>"0",TRIM(N55)="")+AND(J55<>"",J55&""<>"0",TRIM(O55)=""))>0,"Add evidence","Complete"))) | Z55: 1120 | AA55: Managing Directors and Chief Executives | AB55: 112 | AC55: Managing Directors and Chief Executives | AD55: 1 | AE55: Managers | AF55: Not defined | AH55: MES/Q0201
A56: 54 | B56: 1120.3500 | C56: Working Proprietor, Other Services | D56: Working Proprietor, Other Services plans, organizes, co-ordinates and controls activities of the organization, wholly or partly owned by him, and is engaged in running and managing educational institutions; rendering medical and other health services, sanitation, washing and cleaning households, garments, etc. and providing other services. | Y56: =IF(COUNTA(E56:J56,P56:W56)=0,"Not started",IF(COUNTA(E56:J56,P56:W56)<14,"Incomplete",IF((AND(F56<>"",F56&""<>"0",TRIM(K56)="")+AND(G56<>"",G56&""<>"0",TRIM(L56)="")+AND(H56<>"",H56&""<>"0",TRIM(M56)="")+AND(I56<>"",I56&""<>"0",TRIM(N56)="")+AND(J56<>"",J56&""<>"0",TRIM(O56)=""))>0,"Add evidence","Complete"))) | Z56: 1120 | AA56: Managing Directors and Chief Executives | AB56: 112 | AC56: Managing Directors and Chief Executives | AD56: 1 | AE56: Managers | AF56: Not defined | AG56: 1219.10
A57: 55 | B57: 1120.3600 | C57: Director, Other Services | D57: Director, Other Services plans, organizes and controls, within authority delegated, activities of public or private organizations or establishments, or one or more of its departments or branches, engaged in running educational institutions; rendering medical sanitation and other health services. Organizing and providing religious services, promoting welfare of workers or community, giving charity assistance or aid to infirm or orphans. Organizing and managing trade and labour organizations and other civic and social associations, washing and cleaning garments etc., undertaking and cremating; and performing other services. Included are: DIRECTOR OF EDUCATIONAL INSTITUTIONS. DIRECTOR OF CHARITABLE INSTITUTIONS, DIRECTOR, ORPHANAGE DIRECTOR, Y.M.C.A, DIRECTOR, Y.W.C.A. | Y57: =IF(COUNTA(E57:J57,P57:W57)=0,"Not started",IF(COUNTA(E57:J57,P57:W57)<14,"Incomplete",IF((AND(F57<>"",F57&""<>"0",TRIM(K57)="")+AND(G57<>"",G57&""<>"0",TRIM(L57)="")+AND(H57<>"",H57&""<>"0",TRIM(M57)="")+AND(I57<>"",I57&""<>"0",TRIM(N57)="")+AND(J57<>"",J57&""<>"0",TRIM(O57)=""))>0,"Add evidence","Complete"))) | Z57: 1120 | AA57: Managing Directors and Chief Executives | AB57: 112 | AC57: Managing Directors and Chief Executives | AD57: 1 | AE57: Managers | AF57: Not defined | AG57: 1219.20
A58: 56 | B58: 1120.3700 | C58: Director, Museum/Zoo | D58: Director, Museum/Zoo administers affairs of museum, zoo, or similar establishments. Confers with the institution's board of Directors to formulate policies and plan overall operations. Directs acquisition, education, research, public service, and developmental activities of the institution, consulting with curatorial, administrative, and maintenance staff members to implement policies and initiate programmes. Works with members of curatorial and administrative staffs to acquire additions to collections. Confers with administrative staff members to determine budget requirements, plans fund raising drives, prepares applications for grants from government agencies or private foundations, and solicits financial support for institutions. Establishes and maintains contact with administrators of other institutions to exchange information concerning operations and plan, co-ordinate, or consolidate community service and education programmes. Represents the institution at professional and civic social events, conventions, and other gatherings to strengthen relationships with cultural and civic leaders, present lectures or participate in seminars, or explain institution's functions and seek financial support for projects. Reviews materials prepared by staff members, such as articles for journals, requests for grants and reports on institutional programmes, and approves materials or suggests changes. Instructs classes in institution's education programme or as guest lecturer at the university. Writes articles for technical journals or other publications. | Y58: =IF(COUNTA(E58:J58,P58:W58)=0,"Not started",IF(COUNTA(E58:J58,P58:W58)<14,"Incomplete",IF((AND(F58<>"",F58&""<>"0",TRIM(K58)="")+AND(G58<>"",G58&""<>"0",TRIM(L58)="")+AND(H58<>"",H58&""<>"0",TRIM(M58)="")+AND(I58<>"",I58&""<>"0",TRIM(N58)="")+AND(J58<>"",J58&""<>"0",TRIM(O58)=""))>0,"Add evidence","Complete"))) | Z58: 1120 | AA58: Managing Directors and Chief Executives | AB58: 112 | AC58: Managing Directors and Chief Executives | AD58: 1 | AE58: Managers | AF58: Not defined | AG58: 1219.30
A59: 57 | B59: 1120.3800 | C59: Chief Librarian | D59: Chief Librarian plans and administers programme of library services: Submits recommendations on library policies and services to the governing body, such as board of Directors or board of Trustees, and implements policy decisions. Analyses, selects, and executes recommendations of personnel, such as department chiefs or branch supervisors. Co-ordinates activities of the branch or departmental libraries. Analyses and co-ordinates departmental budget estimates and controls expenditures to administer approved budget. Reviews and evaluates orders for books and audio-visual materials. Examines trade publications and materials, interviews publishers' representatives, and consults with others to select materials. Administers personnel regulations, interviews and appoints job applicants and promotes and discharges employees. Plans and conducts staff meetings and participates in community and professional meetings to discuss and act on library problems. Delivers book reviews and lectures to publicise library activities and services. Provides library public relation services. May examine and select materials to be discarded, repaired, or replaced. | Y59: =IF(COUNTA(E59:J59,P59:W59)=0,"Not started",IF(COUNTA(E59:J59,P59:W59)<14,"Incomplete",IF((AND(F59<>"",F59&""<>"0",TRIM(K59)="")+AND(G59<>"",G59&""<>"0",TRIM(L59)="")+AND(H59<>"",H59&""<>"0",TRIM(M59)="")+AND(I59<>"",I59&""<>"0",TRIM(N59)="")+AND(J59<>"",J59&""<>"0",TRIM(O59)=""))>0,"Add evidence","Complete"))) | Z59: 1120 | AA59: Managing Directors and Chief Executives | AB59: 112 | AC59: Managing Directors and Chief Executives | AD59: 1 | AE59: Managers | AF59: Not defined | AG59: 1219.40
A60: 58 | B60: 1120.3900 | C60: Principal, College | D60: Principal College directs and co-ordinates educational, administrative, and counselling activities of college. Develops and evaluates educational programmes to ensure conformance to state and university standards. Develops and co-ordinates educational programmes through meetings with staff, review of teachers' activities, and issuance of directives. Confers with teachers, students, and parents concerning educational and behavioural problems in the college. Establishes and maintains relationships with colleges, community organizations, and other colleges to co-ordinate educational, sports and cultural services. Forwards requisitions and allocates supplies, equipment, and instructional material as needed. Directs preparation of class schedules, cumulative records, and attendance reports. Observes and evaluates teacher’s performance. Interviews and hires teachers. Walks around the college building and property to monitor safety and security. Plans and monitors college budget and financial matters. May plan and direct building maintenance. May develop and administer educational programmes for students with mental or physical handicaps. | Y60: =IF(COUNTA(E60:J60,P60:W60)=0,"Not started",IF(COUNTA(E60:J60,P60:W60)<14,"Incomplete",IF((AND(F60<>"",F60&""<>"0",TRIM(K60)="")+AND(G60<>"",G60&""<>"0",TRIM(L60)="")+AND(H60<>"",H60&""<>"0",TRIM(M60)="")+AND(I60<>"",I60&""<>"0",TRIM(N60)="")+AND(J60<>"",J60&""<>"0",TRIM(O60)=""))>0,"Add evidence","Complete"))) | Z60: 1120 | AA60: Managing Directors and Chief Executives | AB60: 112 | AC60: Managing Directors and Chief Executives | AD60: 1 | AE60: Managers | AF60: Not defined | AG60: 1219.50
A61: 59 | B61: 1120.9900 | C61: Managing Directors and Chief Executives, Others | D61: Working Proprietors and Directors, Other Workers plan, organize, control, co-ordinate and supervise activities of public or private organizations, wholly or partially owned by them or on behalf of others, engaged in generating, transmitting and distributing electricity; producing and supplying gas, purifying and supplying water and providing related services not elsewhere classified. | Y61: =IF(COUNTA(E61:J61,P61:W61)=0,"Not started",IF(COUNTA(E61:J61,P61:W61)<14,"Incomplete",IF((AND(F61<>"",F61&""<>"0",TRIM(K61)="")+AND(G61<>"",G61&""<>"0",TRIM(L61)="")+AND(H61<>"",H61&""<>"0",TRIM(M61)="")+AND(I61<>"",I61&""<>"0",TRIM(N61)="")+AND(J61<>"",J61&""<>"0",TRIM(O61)=""))>0,"Add evidence","Complete"))) | Z61: 1120 | AA61: Managing Directors and Chief Executives | AB61: 112 | AC61: Managing Directors and Chief Executives | AD61: 1 | AE61: Managers | AF61: Not defined | AG61: 1211.90
A62: 60 | B62: 1211.0100 | C62: General Manager, Bank | D62: General Manager, Bank organizes, controls and supervises, within authority delegated, activities of a private or public bank or one or more of its departments or branches. Is designated according to authority delegated or work performed such as: AGENT (BANK) SUB-AGENT (BANK) | Y62: =IF(COUNTA(E62:J62,P62:W62)=0,"Not started",IF(COUNTA(E62:J62,P62:W62)<14,"Incomplete",IF((AND(F62<>"",F62&""<>"0",TRIM(K62)="")+AND(G62<>"",G62&""<>"0",TRIM(L62)="")+AND(H62<>"",H62&""<>"0",TRIM(M62)="")+AND(I62<>"",I62&""<>"0",TRIM(N62)="")+AND(J62<>"",J62&""<>"0",TRIM(O62)=""))>0,"Add evidence","Complete"))) | Z62: 1211 | AA62: Finance Managers | AB62: 121 | AC62: Business Services and Administration Managers | AD62: 1 | AE62: Managers | AF62: Not defined | AG62: 1307.10
A63: 61 | B63: 1211.0200 | C63: General Manager, Insurance | D63: General Manager, Insurance organizes, controls and supervises, within authority delegated, activities of a private or public organization or one or more of its departments or branches, engaged in life, fire, accident, marine and other general insurance business. | Y63: =IF(COUNTA(E63:J63,P63:W63)=0,"Not started",IF(COUNTA(E63:J63,P63:W63)<14,"Incomplete",IF((AND(F63<>"",F63&""<>"0",TRIM(K63)="")+AND(G63<>"",G63&""<>"0",TRIM(L63)="")+AND(H63<>"",H63&""<>"0",TRIM(M63)="")+AND(I63<>"",I63&""<>"0",TRIM(N63)="")+AND(J63<>"",J63&""<>"0",TRIM(O63)=""))>0,"Add evidence","Complete"))) | Z63: 1211 | AA63: Finance Managers | AB63: 121 | AC63: Business Services and Administration Managers | AD63: 1 | AE63: Managers | AF63: Not defined | AG63: 1307.20
A64: 62 | B64: 1211.0300 | C64: Purser, Ship | D64: Purser, Ship deals with correspondence and accounts relating to a ship. Keeps charge of all accounts and pay of the ship's personnel. Checks reports of Clerks and pays of crew and maintains their pay rolls. Prepares portage bills and ship's 30 articles (contracts). Collects mail and distributes to passengers, officers and crew. May supervise stowing or removal of luggage from holds in conjunction with Chief Officer, Ship or Officer on Watch. May collect valuables of passengers for safe custody in passenger ships. May arrange parties and other entertainment for passengers and generally acts as a host. | Y64: =IF(COUNTA(E64:J64,P64:W64)=0,"Not started",IF(COUNTA(E64:J64,P64:W64)<14,"Incomplete",IF((AND(F64<>"",F64&""<>"0",TRIM(K64)="")+AND(G64<>"",G64&""<>"0",TRIM(L64)="")+AND(H64<>"",H64&""<>"0",TRIM(M64)="")+AND(I64<>"",I64&""<>"0",TRIM(N64)="")+AND(J64<>"",J64&""<>"0",TRIM(O64)=""))>0,"Add evidence","Complete"))) | Z64: 1211 | AA64: Finance Managers | AB64: 121 | AC64: Business Services and Administration Managers | AD64: 1 | AE64: Managers | AF64: Not defined | AG64: 1231.10
A65: 63 | B65: 1211.9900 | C65: Finance and Administration Managers, Others | D65: Finance and Administration Department Managers, Others include Managers engaged in finance and administration and related services, not elsewhere classified. | Y65: =IF(COUNTA(E65:J65,P65:W65)=0,"Not started",IF(COUNTA(E65:J65,P65:W65)<14,"Incomplete",IF((AND(F65<>"",F65&""<>"0",TRIM(K65)="")+AND(G65<>"",G65&""<>"0",TRIM(L65)="")+AND(H65<>"",H65&""<>"0",TRIM(M65)="")+AND(I65<>"",I65&""<>"0",TRIM(N65)="")+AND(J65<>"",J65&""<>"0",TRIM(O65)=""))>0,"Add evidence","Complete"))) | Z65: 1211 | AA65: Finance Managers | AB65: 121 | AC65: Business Services and Administration Managers | AD65: 1 | AE65: Managers | AF65: Not defined
A66: 64 | B66: 1212.0100 | C66: Personnel Manager | D66: Personnel Manager; Personnel Officer; Industrial Relation Officer formulates and executes policies relating to recruitment, training, review of terms and conditions of employment of personnel, implementation of statutory and other welfare schemes and effective utilization and discharge of personnel employed in any undertaking. Advises and assists in development of managerial power, prescribes recruitment methods, organizes training schemes, supervises administration of welfare programmes, distributes personnel for their effective utilization in organization and resolves problems of remuneration, discipline and industrial disputes in accordance with established laws. Investigates in to specific problems of indiscipline and inefficiency to evolve and suggest ameliorative measures to management. Establishes channels of consultation between labour and employers to minimize misunderstanding, promote cordial relations and consults with labour representatives on behalf of employers to remove causes of petty grievances. May specialize in a particular function, such as employment and placement, training, welfare, or industrial relations and be designated accordingly. | Y66: =IF(COUNTA(E66:J66,P66:W66)=0,"Not started",IF(COUNTA(E66:J66,P66:W66)<14,"Incomplete",IF((AND(F66<>"",F66&""<>"0",TRIM(K66)="")+AND(G66<>"",G66&""<>"0",TRIM(L66)="")+AND(H66<>"",H66&""<>"0",TRIM(M66)="")+AND(I66<>"",I66&""<>"0",TRIM(N66)="")+AND(J66<>"",J66&""<>"0",TRIM(O66)=""))>0,"Add evidence","Complete"))) | Z66: 1212 | AA66: Human Resource Managers | AB66: 121 | AC66: Business Services and Administration Managers | AD66: 1 | AE66: Managers | AF66: Not defined | AG66: 1232.10
A67: 65 | B67: 1212.9900 | C67: Personnel and Industrial Relations Managers, Other | D67: Personnel and Industrial Relation Managers, Other include managers engaged in personnel and industrial relations and related services, not elsewhere classified. | Y67: =IF(COUNTA(E67:J67,P67:W67)=0,"Not started",IF(COUNTA(E67:J67,P67:W67)<14,"Incomplete",IF((AND(F67<>"",F67&""<>"0",TRIM(K67)="")+AND(G67<>"",G67&""<>"0",TRIM(L67)="")+AND(H67<>"",H67&""<>"0",TRIM(M67)="")+AND(I67<>"",I67&""<>"0",TRIM(N67)="")+AND(J67<>"",J67&""<>"0",TRIM(O67)=""))>0,"Add evidence","Complete"))) | Z67: 1212 | AA67: Human Resource Managers | AB67: 121 | AC67: Business Services and Administration Managers | AD67: 1 | AE67: Managers | AF67: Not defined | AG67: 1232.90
A68: 66 | B68: 1213.0100 | C68: Manager, Automotive Service | D68: Manager, Automotive Services directs and co-ordinates activities concerned with acquisition of automotive equipment and operation and maintenance of automotive fleet repair and storage facilities for public utility, transportation, commercial, or industrial companies. Co-ordinates activities of staff personnel conducting research and testing programme on automotive equipment considered for acquisition for such factors as operational performance, operational and maintenance costs, safety of operation, and compliance with environmental laws and regulations. Reviews and submits staff proposals for modifications to vendor or manufacturer. Directs procurement of all types of company-owned-and-operated automotive equipment, materials, supplies, and parts required to maintain automotive equipment, garages, and storage facilities. Co-ordinates automotive repair and maintenance services to obtain maximum utilisation of automotive equipment and prevent operational delays in other departments. | Y68: =IF(COUNTA(E68:J68,P68:W68)=0,"Not started",IF(COUNTA(E68:J68,P68:W68)<14,"Incomplete",IF((AND(F68<>"",F68&""<>"0",TRIM(K68)="")+AND(G68<>"",G68&""<>"0",TRIM(L68)="")+AND(H68<>"",H68&""<>"0",TRIM(M68)="")+AND(I68<>"",I68&""<>"0",TRIM(N68)="")+AND(J68<>"",J68&""<>"0",TRIM(O68)=""))>0,"Add evidence","Complete"))) | Z68: 1213 | AA68: Policy and Planning Managers | AB68: 121 | AC68: Business Services and Administration Managers | AD68: 1 | AE68: Managers | AF68: Not defined | AG68: 1239.10
A69: 67 | B69: 1213.0101 | C69: Quality Assurance Standards In Charge | D69: Quality Assurance Standards In Charge is responsible for selecting, maintaining and monitoring the measuring systems to be used for the inspection of manufactured products in order to assure quality products to customers. | Y69: =IF(COUNTA(E69:J69,P69:W69)=0,"Not started",IF(COUNTA(E69:J69,P69:W69)<14,"Incomplete",IF((AND(F69<>"",F69&""<>"0",TRIM(K69)="")+AND(G69<>"",G69&""<>"0",TRIM(L69)="")+AND(H69<>"",H69&""<>"0",TRIM(M69)="")+AND(I69<>"",I69&""<>"0",TRIM(N69)="")+AND(J69<>"",J69&""<>"0",TRIM(O69)=""))>0,"Add evidence","Complete"))) | Z69: 1213 | AA69: Policy and Planning Managers | AB69: 121 | AC69: Business Services and Administration Managers | AD69: 1 | AE69: Managers | AF69: Not defined | AH69: ASC/Q6305
A70: 68 | B70: 1213.0102 | C70: Manager-Customer Quality | D70: Manager-Customer Quality is responsible for the quality inspection, performance and improvement of final products delivered to customers. | Y70: =IF(COUNTA(E70:J70,P70:W70)=0,"Not started",IF(COUNTA(E70:J70,P70:W70)<14,"Incomplete",IF((AND(F70<>"",F70&""<>"0",TRIM(K70)="")+AND(G70<>"",G70&""<>"0",TRIM(L70)="")+AND(H70<>"",H70&""<>"0",TRIM(M70)="")+AND(I70<>"",I70&""<>"0",TRIM(N70)="")+AND(J70<>"",J70&""<>"0",TRIM(O70)=""))>0,"Add evidence","Complete"))) | Z70: 1213 | AA70: Policy and Planning Managers | AB70: 121 | AC70: Business Services and Administration Managers | AD70: 1 | AE70: Managers | AF70: Not defined | AH70: ASC/Q6304
A71: 69 | B71: 1213.0200 | C71: Manager, Automotive Service Station | D71: Manager, Automotive Service Station manages automobile service stations. Plans, develops, and implements policies for operating station, such as hours of operation, workers required and duties, scope of operations, and prices for products and services. Hires and trains workers, prepares work schedules, and assigns workers to specific duties, such as customer service, automobile maintenance, or repair work. Directs, co-ordinates, and participates in performing customer service activities, such as pumping petroleum fuel, checking engine oil, tires, battery, and washing windows and windshield. Notifies customers when oil is dirty or low, tires are worn, hoses or fan-belts are defective, or evidence indicates battery defects. Promotes sale of products and services, such as oil change and lubrication, tires, battery, or other automotive accessories. Reconciles cash with petrol pump meter readings, sales slips, and credit card charges. Orders, receives, and inventories petroleum fuel, oil, automotive accessories and parts. May perform automotive maintenance and repair work, such as adjusting or relining brakes, motor tune-ups, valve grinding, and changing and repairing tires. | Y71: =IF(COUNTA(E71:J71,P71:W71)=0,"Not started",IF(COUNTA(E71:J71,P71:W71)<14,"Incomplete",IF((AND(F71<>"",F71&""<>"0",TRIM(K71)="")+AND(G71<>"",G71&""<>"0",TRIM(L71)="")+AND(H71<>"",H71&""<>"0",TRIM(M71)="")+AND(I71<>"",I71&""<>"0",TRIM(N71)="")+AND(J71<>"",J71&""<>"0",TRIM(O71)=""))>0,"Add evidence","Complete"))) | Z71: 1213 | AA71: Policy and Planning Managers | AB71: 121 | AC71: Business Services and Administration Managers | AD71: 1 | AE71: Managers | AF71: Not defined | AG71: 1239.20
A72: 70 | B72: 1213.0201 | C72: Area Service Manager | D72: Area Service Manager is responsible for supervising and handling overall services network of the assigned area. The individual generally monitors services network at dealerships and reviews and supervises processes. | Y72: =IF(COUNTA(E72:J72,P72:W72)=0,"Not started",IF(COUNTA(E72:J72,P72:W72)<14,"Incomplete",IF((AND(F72<>"",F72&""<>"0",TRIM(K72)="")+AND(G72<>"",G72&""<>"0",TRIM(L72)="")+AND(H72<>"",H72&""<>"0",TRIM(M72)="")+AND(I72<>"",I72&""<>"0",TRIM(N72)="")+AND(J72<>"",J72&""<>"0",TRIM(O72)=""))>0,"Add evidence","Complete"))) | Z72: 1213 | AA72: Policy and Planning Managers | AB72: 121 | AC72: Business Services and Administration Managers | AD72: 1 | AE72: Managers | AF72: Not defined | AH72: ASC/Q0603
A73: 71 | B73: 1213.0202 | C73: Territory Service Manager | D73: Territory Service Manager is responsible for managing the service function in the assigned territory. The individual supervises service functions at the dealership network of the assigned territory and helps in increasing profitability. | Y73: =IF(COUNTA(E73:J73,P73:W73)=0,"Not started",IF(COUNTA(E73:J73,P73:W73)<14,"Incomplete",IF((AND(F73<>"",F73&""<>"0",TRIM(K73)="")+AND(G73<>"",G73&""<>"0",TRIM(L73)="")+AND(H73<>"",H73&""<>"0",TRIM(M73)="")+AND(I73<>"",I73&""<>"0",TRIM(N73)="")+AND(J73<>"",J73&""<>"0",TRIM(O73)=""))>0,"Add evidence","Complete"))) | Z73: 1213 | AA73: Policy and Planning Managers | AB73: 121 | AC73: Business Services and Administration Managers | AD73: 1 | AE73: Managers | AF73: Not defined | AH73: ASC/Q0602
A74: 72 | B74: 1213.9900 | C74: Managers, Other Services | D74: Managers, Other Services include Department Managers not elsewhere classified. | Y74: =IF(COUNTA(E74:J74,P74:W74)=0,"Not started",IF(COUNTA(E74:J74,P74:W74)<14,"Incomplete",IF((AND(F74<>"",F74&""<>"0",TRIM(K74)="")+AND(G74<>"",G74&""<>"0",TRIM(L74)="")+AND(H74<>"",H74&""<>"0",TRIM(M74)="")+AND(I74<>"",I74&""<>"0",TRIM(N74)="")+AND(J74<>"",J74&""<>"0",TRIM(O74)=""))>0,"Add evidence","Complete"))) | Z74: 1213 | AA74: Policy and Planning Managers | AB74: 121 | AC74: Business Services and Administration Managers | AD74: 1 | AE74: Managers | AF74: Not defined | AG74: 1239.90
A75: 73 | B75: 1219.0100 | C75: Manager, Import and Export | D75: Manager, Import and Export co-ordinates activities of international traffic division of import-export agencies and negotiates settlements between foreign and domestic shippers: Plans and directs flow of air and surface traffic moving to overseas destinations. Supervises workers engaged in receiving and shipping freight, documentation, way billing, assessing charges, and collecting fees for shipments. Negotiates with domestic customers, as intermediary for foreign customers, to resolve problems and arrives at mutual agreements. Negotiates with foreign shipping interests to contract for reciprocal freight-handling agreements. May examine invoices and shipping manifests for conformity to tariff and customs regulations. May contact customs officials to effect release of incoming freight and resolve customs delays. May prepare reports of transactions to facilitate billing of shippers and foreign carriers. | Y75: =IF(COUNTA(E75:J75,P75:W75)=0,"Not started",IF(COUNTA(E75:J75,P75:W75)<14,"Incomplete",IF((AND(F75<>"",F75&""<>"0",TRIM(K75)="")+AND(G75<>"",G75&""<>"0",TRIM(L75)="")+AND(H75<>"",H75&""<>"0",TRIM(M75)="")+AND(I75<>"",I75&""<>"0",TRIM(N75)="")+AND(J75<>"",J75&""<>"0",TRIM(O75)=""))>0,"Add evidence","Complete"))) | Z75: 1219 | AA75: Business Services and Administration Managers Not Elsewhere Classified | AB75: 121 | AC75: Business Services and Administration Managers | AD75: 1 | AE75: Managers | AF75: Not defined | AG75: 1227.30
A76: 74 | B76: 1219.0101 | C76: Export Manager | D76: Export Manager is responsible for leading and managing the entire process of international shipment of goods. Their work includes analysis of the foreign trade logistics, management and supervision of all shipment related documents and ensuring shipping compliance. | Y76: =IF(COUNTA(E76:J76,P76:W76)=0,"Not started",IF(COUNTA(E76:J76,P76:W76)<14,"Incomplete",IF((AND(F76<>"",F76&""<>"0",TRIM(K76)="")+AND(G76<>"",G76&""<>"0",TRIM(L76)="")+AND(H76<>"",H76&""<>"0",TRIM(M76)="")+AND(I76<>"",I76&""<>"0",TRIM(N76)="")+AND(J76<>"",J76&""<>"0",TRIM(O76)=""))>0,"Add evidence","Complete"))) | Z76: 1219 | AA76: Business Services and Administration Managers Not Elsewhere Classified | AB76: 121 | AC76: Business Services and Administration Managers | AD76: 1 | AE76: Managers | AF76: Not defined | AH76: AMH/Q1603
A77: 75 | B77: 1219.0200 | C77: Manager, Health Club/Manager, Fitness Club/Centre/Gym | D77: Manager, Health Club supervises and co-ordinates activities of workers engaged in planning, selling, and instructing fitness plans for clients of health clubs: Assigns and adjusts work schedules to meet customer demand. Interviews, hires, and trains new employees. Observes workers in their performance of duties and gives remedial training to correct worker deficiencies and ensures courteous service to patrons. Plans and sells figure-controlling programmes to prospective patrons. Assists subordinates in interviewing, measuring, and evaluating patrons' physical condition to determine appropriate fitness programmes. Prepares contract forms, obtains signatures, collects deposits, and issues membership cards to patrons accepting plans. Demonstrates operation and explains purpose of equipment, such as treadmill exerciser and stationary bicycle, and instructs patrons in their use. Monitors patron's exercise programme to ensure adherence to specified techniques. | Y77: =IF(COUNTA(E77:J77,P77:W77)=0,"Not started",IF(COUNTA(E77:J77,P77:W77)<14,"Incomplete",IF((AND(F77<>"",F77&""<>"0",TRIM(K77)="")+AND(G77<>"",G77&""<>"0",TRIM(L77)="")+AND(H77<>"",H77&""<>"0",TRIM(M77)="")+AND(I77<>"",I77&""<>"0",TRIM(N77)="")+AND(J77<>"",J77&""<>"0",TRIM(O77)=""))>0,"Add evidence","Complete"))) | Z77: 1219 | AA77: Business Services and Administration Managers Not Elsewhere Classified | AB77: 121 | AC77: Business Services and Administration Managers | AD77: 1 | AE77: Managers | AF77: Not defined | AG77: 1228.10
A78: 76 | B78: 1221.0100 | C78: Sales Manager (Wholesale Trade) | D78: Sales Manager (Wholesale Trade) organizes and manages wholesale trade organizations, or one or more if its branches or departments engaged in buying goods and selling them for profits to retailers or industrial and commercial consumers. | Y78: =IF(COUNTA(E78:J78,P78:W78)=0,"Not started",IF(COUNTA(E78:J78,P78:W78)<14,"Incomplete",IF((AND(F78<>"",F78&""<>"0",TRIM(K78)="")+AND(G78<>"",G78&""<>"0",TRIM(L78)="")+AND(H78<>"",H78&""<>"0",TRIM(M78)="")+AND(I78<>"",I78&""<>"0",TRIM(N78)="")+AND(J78<>"",J78&""<>"0",TRIM(O78)=""))>0,"Add evidence","Complete"))) | Z78: 1221 | AA78: Sales and Marketing Managers | AB78: 122 | AC78: Sales, Marketing and Development Managers | AD78: 1 | AE78: Managers | AF78: Not defined | AG78: 1233.10
A79: 77 | B79: 1221.0200 | C79: Sales Manager (Retail Trade) | D79: Sales Manager (Retail Trade) organizes and manages retail trade organization, or one or more of its branches or departments, engaged in buying goods and merchandise and selling them for profit to customers. | Y79: =IF(COUNTA(E79:J79,P79:W79)=0,"Not started",IF(COUNTA(E79:J79,P79:W79)<14,"Incomplete",IF((AND(F79<>"",F79&""<>"0",TRIM(K79)="")+AND(G79<>"",G79&""<>"0",TRIM(L79)="")+AND(H79<>"",H79&""<>"0",TRIM(M79)="")+AND(I79<>"",I79&""<>"0",TRIM(N79)="")+AND(J79<>"",J79&""<>"0",TRIM(O79)=""))>0,"Add evidence","Complete"))) | Z79: 1221 | AA79: Sales and Marketing Managers | AB79: 122 | AC79: Sales, Marketing and Development Managers | AD79: 1 | AE79: Managers | AF79: Not defined | AG79: 1233.20
A80: 78 | B80: 1221.0301 | C80: Home Delivery Manager | D80: Home Delivery Manager is responsible for delivering vehicles to the customers and explaining all service related activities to the customer, while delivering the vehicle. They also ensure proper pickup and delivery of vehicles as per the customers’ service schedule. | Y80: =IF(COUNTA(E80:J80,P80:W80)=0,"Not started",IF(COUNTA(E80:J80,P80:W80)<14,"Incomplete",IF((AND(F80<>"",F80&""<>"0",TRIM(K80)="")+AND(G80<>"",G80&""<>"0",TRIM(L80)="")+AND(H80<>"",H80&""<>"0",TRIM(M80)="")+AND(I80<>"",I80&""<>"0",TRIM(N80)="")+AND(J80<>"",J80&""<>"0",TRIM(O80)=""))>0,"Add evidence","Complete"))) | Z80: 1221 | AA80: Sales and Marketing Managers | AB80: 122 | AC80: Sales, Marketing and Development Managers | AD80: 1 | AE80: Managers | AF80: Not defined | AH80: ASC/Q1006
A81: 79 | B81: 1221.0401 | C81: Territory Sales Manager (Broadband) | D81: Territory Sales Manager (Broadband) manages and supervises DSAs activities and achievement of sales targets, in the assigned territory. Enhances Average Revenue Per User (ARPU) and customer base, channel development and process compliance. | Y81: =IF(COUNTA(E81:J81,P81:W81)=0,"Not started",IF(COUNTA(E81:J81,P81:W81)<14,"Incomplete",IF((AND(F81<>"",F81&""<>"0",TRIM(K81)="")+AND(G81<>"",G81&""<>"0",TRIM(L81)="")+AND(H81<>"",H81&""<>"0",TRIM(M81)="")+AND(I81<>"",I81&""<>"0",TRIM(N81)="")+AND(J81<>"",J81&""<>"0",TRIM(O81)=""))>0,"Add evidence","Complete"))) | Z81: 1221 | AA81: Sales and Marketing Managers | AB81: 122 | AC81: Sales, Marketing and Development Managers | AD81: 1 | AE81: Managers | AF81: Not defined | AH81: TEL/Q0204
A82: 80 | B82: 1221.0501 | C82: Territory Sales Manager (Prepaid) | D82: Territory Sales Manager (Prepaid) is responsible for distribution expansion and co-ordination with urban distributors, i.e. multi brand distributors, to achieve sales targets in the assigned territory achieving revenue targets people development channel management retailer education range selling increasing customer base and process compliance. (Rural Distributor)-Individual at this job is responsible for similar activities but with rural i.e. company specific distributors | Y82: =IF(COUNTA(E82:J82,P82:W82)=0,"Not started",IF(COUNTA(E82:J82,P82:W82)<14,"Incomplete",IF((AND(F82<>"",F82&""<>"0",TRIM(K82)="")+AND(G82<>"",G82&""<>"0",TRIM(L82)="")+AND(H82<>"",H82&""<>"0",TRIM(M82)="")+AND(I82<>"",I82&""<>"0",TRIM(N82)="")+AND(J82<>"",J82&""<>"0",TRIM(O82)=""))>0,"Add evidence","Complete"))) | Z82: 1221 | AA82: Sales and Marketing Managers | AB82: 122 | AC82: Sales, Marketing and Development Managers | AD82: 1 | AE82: Managers | AF82: Not defined | AH82: TEL/Q0203
A83: 81 | B83: 1221.0601 | C83: Sales Co-ordinator (Media Org) | D83: Sales Co-ordinator (Media Org) is responsible for back-end sales activities | Y83: =IF(COUNTA(E83:J83,P83:W83)=0,"Not started",IF(COUNTA(E83:J83,P83:W83)<14,"Incomplete",IF((AND(F83<>"",F83&""<>"0",TRIM(K83)="")+AND(G83<>"",G83&""<>"0",TRIM(L83)="")+AND(H83<>"",H83&""<>"0",TRIM(M83)="")+AND(I83<>"",I83&""<>"0",TRIM(N83)="")+AND(J83<>"",J83&""<>"0",TRIM(O83)=""))>0,"Add evidence","Complete"))) | Z83: 1221 | AA83: Sales and Marketing Managers | AB83: 122 | AC83: Sales, Marketing and Development Managers | AD83: 1 | AE83: Managers | AF83: Not defined | AH83: MES/Q0204
A84: 82 | B84: 1221.0602 | C84: Sales Manager (Media Org) | D84: Sales Manager (Media Org) is responsible to lead sales activities within the designated area of responsibility | Y84: =IF(COUNTA(E84:J84,P84:W84)=0,"Not started",IF(COUNTA(E84:J84,P84:W84)<14,"Incomplete",IF((AND(F84<>"",F84&""<>"0",TRIM(K84)="")+AND(G84<>"",G84&""<>"0",TRIM(L84)="")+AND(H84<>"",H84&""<>"0",TRIM(M84)="")+AND(I84<>"",I84&""<>"0",TRIM(N84)="")+AND(J84<>"",J84&""<>"0",TRIM(O84)=""))>0,"Add evidence","Complete"))) | Z84: 1221 | AA84: Sales and Marketing Managers | AB84: 122 | AC84: Sales, Marketing and Development Managers | AD84: 1 | AE84: Managers | AF84: Not defined | AH84: MES/Q0202
A85: 83 | B85: 1221.9900 | C85: Sales and Marketing Managers, Other | D85: Sales and Marketing Managers, Other include managers engaged in sales and marketing and related services, not elsewhere classified. | Y85: =IF(COUNTA(E85:J85,P85:W85)=0,"Not started",IF(COUNTA(E85:J85,P85:W85)<14,"Incomplete",IF((AND(F85<>"",F85&""<>"0",TRIM(K85)="")+AND(G85<>"",G85&""<>"0",TRIM(L85)="")+AND(H85<>"",H85&""<>"0",TRIM(M85)="")+AND(I85<>"",I85&""<>"0",TRIM(N85)="")+AND(J85<>"",J85&""<>"0",TRIM(O85)=""))>0,"Add evidence","Complete"))) | Z85: 1221 | AA85: Sales and Marketing Managers | AB85: 122 | AC85: Sales, Marketing and Development Managers | AD85: 1 | AE85: Managers | AF85: Not defined | AG85: 1233.90
A86: 84 | B86: 1222.0100 | C86: Manager, Advertising and Promotion | D86: Manager, Advertising and Promotion plan and direct advertising policies and programmes or produce collateral materials, such as posters, contests, coupons, or give-aways, to create extra interest in the purchase of a product or service for a department, an entire organization, or on an account basis. Confer with clients to provide marketing or technical advice. Confer with department heads and/or staff to discuss topics such as contracts, selection of advertising media, or product to be advertised. Co-ordinate activities of departments, such as sales, graphic arts, media, finance, and research. Co-ordinate with the media to disseminate advertising. Formulate plans to extend business with established accounts and to transact business as agent for advertising accounts. Gather and organize information to plan advertising campaigns. Identify and develop contacts for promotional campaigns and industry programmes that meet identified buyer targets such as dealers, distributors, or consumers. Inspect layouts and advertising copy and edit scripts, audio and video tapes, and other promotional material for adherence to specifications. Monitor and analyse sales promotion results to determine cost effectiveness of promotional campaigns. Plan and execute advertising policies and strategies for organizations. | Y86: =IF(COUNTA(E86:J86,P86:W86)=0,"Not started",IF(COUNTA(E86:J86,P86:W86)<14,"Incomplete",IF((AND(F86<>"",F86&""<>"0",TRIM(K86)="")+AND(G86<>"",G86&""<>"0",TRIM(L86)="")+AND(H86<>"",H86&""<>"0",TRIM(M86)="")+AND(I86<>"",I86&""<>"0",TRIM(N86)="")+AND(J86<>"",J86&""<>"0",TRIM(O86)=""))>0,"Add evidence","Complete"))) | Z86: 1222 | AA86: Advertising and Public Relation Managers | AB86: 122 | AC86: Sales, Marketing and Development Managers | AD86: 1 | AE86: Managers | AF86: Not defined | AG86: 1234.10
A87: 85 | B87: 1222.0102 | C87: Advertising Operations Coordinator (Digital) | D87: Advertising Operations Co-ordinator (Digital) is responsible for implementing online advertisement campaigns | Y87: =IF(COUNTA(E87:J87,P87:W87)=0,"Not started",IF(COUNTA(E87:J87,P87:W87)<14,"Incomplete",IF((AND(F87<>"",F87&""<>"0",TRIM(K87)="")+AND(G87<>"",G87&""<>"0",TRIM(L87)="")+AND(H87<>"",H87&""<>"0",TRIM(M87)="")+AND(I87<>"",I87&""<>"0",TRIM(N87)="")+AND(J87<>"",J87&""<>"0",TRIM(O87)=""))>0,"Add evidence","Complete"))) | Z87: 1222 | AA87: Advertising and Public Relation Managers | AB87: 122 | AC87: Sales, Marketing and Development Managers | AD87: 1 | AE87: Managers | AF87: Not defined | AH87: MES/Q0206
A88: 86 | B88: 1222.0200 | C88: Manager, Fashion/Fashion Manager | D88: Manager, Fashion promotes new fashions and co-ordinates promotional activities, such as fashion shows, to induce consumer acceptance: Studies fashion and trade journals, travels to garment centres, attends fashion shows, and visits manufacturers and merchandise markets to obtain information on fashion trends. Consults with buying personnel to gain advice regarding type of fashion. Advises publicity and display departments of merchandise to be publicized. Selects garments and accessories to be displayed at fashion shows. Provides information on current fashion, style trends, and use of accessories. May contract with models, musicians, caterers, and other personnel to manage staging of shows. May conduct teenage fashion shows and direct activities of store-sponsored club for teenaged girls. | Y88: =IF(COUNTA(E88:J88,P88:W88)=0,"Not started",IF(COUNTA(E88:J88,P88:W88)<14,"Incomplete",IF((AND(F88<>"",F88&""<>"0",TRIM(K88)="")+AND(G88<>"",G88&""<>"0",TRIM(L88)="")+AND(H88<>"",H88&""<>"0",TRIM(M88)="")+AND(I88<>"",I88&""<>"0",TRIM(N88)="")+AND(J88<>"",J88&""<>"0",TRIM(O88)=""))>0,"Add evidence","Complete"))) | Z88: 1222 | AA88: Advertising and Public Relation Managers | AB88: 122 | AC88: Sales, Marketing and Development Managers | AD88: 1 | AE88: Managers | AF88: Not defined | AG88: 1234.20
A89: 87 | B89: 1222.9900 | C89: Advertising and Public Relations Department Managers, Others | D89: Advertising and Public Relations Department Managers, Other include managers engaged in advertising and public relations and related services, not elsewhere classified. | Y89: =IF(COUNTA(E89:J89,P89:W89)=0,"Not started",IF(COUNTA(E89:J89,P89:W89)<14,"Incomplete",IF((AND(F89<>"",F89&""<>"0",TRIM(K89)="")+AND(G89<>"",G89&""<>"0",TRIM(L89)="")+AND(H89<>"",H89&""<>"0",TRIM(M89)="")+AND(I89<>"",I89&""<>"0",TRIM(N89)="")+AND(J89<>"",J89&""<>"0",TRIM(O89)=""))>0,"Add evidence","Complete"))) | Z89: 1222 | AA89: Advertising and Public Relation Managers | AB89: 122 | AC89: Sales, Marketing and Development Managers | AD89: 1 | AE89: Managers | AF89: Not defined | AG89: 1234.90
A90: 88 | B90: 1223.0101 | C90: Manager Testing Facility | D90: Manager Testing Facility needs to manage requirements identification, development and installation of testing facilities in R&D for validating the specifications of the product. | Y90: =IF(COUNTA(E90:J90,P90:W90)=0,"Not started",IF(COUNTA(E90:J90,P90:W90)<14,"Incomplete",IF((AND(F90<>"",F90&""<>"0",TRIM(K90)="")+AND(G90<>"",G90&""<>"0",TRIM(L90)="")+AND(H90<>"",H90&""<>"0",TRIM(M90)="")+AND(I90<>"",I90&""<>"0",TRIM(N90)="")+AND(J90<>"",J90&""<>"0",TRIM(O90)=""))>0,"Add evidence","Complete"))) | Z90: 1223 | AA90: Research and Development Managers | AB90: 122 | AC90: Sales, Marketing and Development Managers | AD90: 1 | AE90: Managers | AF90: Not defined | AH90: ASC/Q6503
A91: 89 | B91: 1223.0102 | C91: Manager Material Testing | D91: Manager Material Testing needs to administer metallurgical testing, chemical testing and failure analysis of materials for fabrication of parts and other components that finally go into manufacturing of different products. | Y91: =IF(COUNTA(E91:J91,P91:W91)=0,"Not started",IF(COUNTA(E91:J91,P91:W91)<14,"Incomplete",IF((AND(F91<>"",F91&""<>"0",TRIM(K91)="")+AND(G91<>"",G91&""<>"0",TRIM(L91)="")+AND(H91<>"",H91&""<>"0",TRIM(M91)="")+AND(I91<>"",I91&""<>"0",TRIM(N91)="")+AND(J91<>"",J91&""<>"0",TRIM(O91)=""))>0,"Add evidence","Complete"))) | Z91: 1223 | AA91: Research and Development Managers | AB91: 122 | AC91: Sales, Marketing and Development Managers | AD91: 1 | AE91: Managers | AF91: Not defined | AH91: ASC/Q6502
A92: 90 | B92: 1223.0201 | C92: Research Associate | D92: Research Associate is responsible for supporting research activities in a particular scientific field based on the requirement of the organization. The job also involves going through many reports, analysing and interpreting data, creating research reports and documents | Y92: =IF(COUNTA(E92:J92,P92:W92)=0,"Not started",IF(COUNTA(E92:J92,P92:W92)<14,"Incomplete",IF((AND(F92<>"",F92&""<>"0",TRIM(K92)="")+AND(G92<>"",G92&""<>"0",TRIM(L92)="")+AND(H92<>"",H92&""<>"0",TRIM(M92)="")+AND(I92<>"",I92&""<>"0",TRIM(N92)="")+AND(J92<>"",J92&""<>"0",TRIM(O92)=""))>0,"Add evidence","Complete"))) | Z92: 1223 | AA92: Research and Development Managers | AB92: 122 | AC92: Sales, Marketing and Development Managers | AD92: 1 | AE92: Managers | AF92: Not defined | AH92: SSC/Q5301
A93: 91 | B93: 1311.0100 | C93: General Manager, Plantation | D93: General Manager, Plantation manages plantation on behalf of employer. Examines soil, climatic conditions, scope for marketing, etc. to determine type of crop such as tea, coffee, rubber etc. to be grown. Selects, purchases and stores seeds, fertilisers, agricultural implements, etc. as required. Organizes operation of ploughing, manuring, planting etc. Supervises operations of manure preparation, weeding, spraying insecticides and other measures to protect crops from wild animals and plant diseases. Organizes and supervises processes like tapping, threshing, plucking, withering, rolling, shifting, drying, cutting, sorting and storing of harvested produces. Undertakes publicity measures to publicise and to find out market for products and arranges for their transport. Organizes and supervises construction of buildings, quarters, roads, tanks, installation of electric and telephone lines, etc. Supervises and co-ordinates work of field and office staff. Recruits staff and teaches them modern methods of plantation and allocates work. Keeps equipment, fences, building, etc. in order. Maintains muster roll of labour and looks after office correspondence. Looks after welfare of labour and ensures that provisions of Plantation Act, Labour Act, etc. are observed. Ensures proper payment to labour. Pays various taxes to Government and fulfils other obligations, if any. Maintains production and cost statements and submits periodical reports to proprietor. May specialize in growing particular type of plantation such as rubber, tea, coffee, etc. May conduct research and organize demonstration. May arrange preservation of produce. May partially process produce prior to marketing. | Y93: =IF(COUNTA(E93:J93,P93:W93)=0,"Not started",IF(COUNTA(E93:J93,P93:W93)<14,"Incomplete",IF((AND(F93<>"",F93&""<>"0",TRIM(K93)="")+AND(G93<>"",G93&""<>"0",TRIM(L93)="")+AND(H93<>"",H93&""<>"0",TRIM(M93)="")+AND(I93<>"",I93&""<>"0",TRIM(N93)="")+AND(J93<>"",J93&""<>"0",TRIM(O93)=""))>0,"Add evidence","Complete"))) | Z93: 1311 | AA93: Agricultural and Forestry Production Managers | AB93: 131 | AC93: Production Managers in Agriculture, Forestry and Fisheries | AD93: 1 | AE93: Managers | AF93: Not defined | AG93: 1301.20
A94: 92 | B94: 1311.0200 | C94: General Manager, Horticulture | D94: General Manager, Horticulture organizes and supervises planting, maintenance and growth of fruit plants and arranges for marketing of produce. Determines types of fruits or nuts to be grown depending on nature of soil and climate, irrigation and market facilities. Selects and purchases plants, fertilisers and agricultural implements. Organizes operations of ploughing, manuring, sowing or planting and watering. Devises ways and means to supply regular flow of water for irrigation. Supervises agricultural operations such as weeding, spraying insecticides, manuring and harvesting. Selects best market for produce and arranges its transport. Supervises and controls field and office staff. Trains field workers in latest methods of grafting and planting of trees. Attends to office correspondence and keeps cost and production account. Keeps equipment and building, etc. in good order. Pays various taxes and dues and fulfils other obligations. May specialize in growing particular types of fruits. May conduct research and organize field demonstration. May arrange preservation of fruits by canning or in cold storage. May develop variety of fruit trees by grafting and budding. | Y94: =IF(COUNTA(E94:J94,P94:W94)=0,"Not started",IF(COUNTA(E94:J94,P94:W94)<14,"Incomplete",IF((AND(F94<>"",F94&""<>"0",TRIM(K94)="")+AND(G94<>"",G94&""<>"0",TRIM(L94)="")+AND(H94<>"",H94&""<>"0",TRIM(M94)="")+AND(I94<>"",I94&""<>"0",TRIM(N94)="")+AND(J94<>"",J94&""<>"0",TRIM(O94)=""))>0,"Add evidence","Complete"))) | Z94: 1311 | AA94: Agricultural and Forestry Production Managers | AB94: 131 | AC94: Production Managers in Agriculture, Forestry and Fisheries | AD94: 1 | AE94: Managers | AF94: Not defined | AG94: 1301.30
A95: 93 | B95: 1311.0300 | C95: General Manager, Agricultural Farm | D95: General Manager, Agricultural Farm plans, organizes and controls, co-ordinates operations and staff employed in 33 growing agricultural produce on small-scale farm on behalf of Government or other employers. Determines crops to be grown after examining soil, irrigational facilities, climatic conditions and scope for marketing. Selects, purchases and stores seeds, fertilisers and agricultural implements. Organizes ploughing, manuring, sowing and watering. Devises ways and means to irrigate cultivation from well, tank, reservoir or other source of water supply. Supervises operations of manure preparation, weeding, spraying insecticides and other measures protecting crops from wild animals, harvesting, threshing winnowing, bagging, storing etc. Finds out market for cultivated products and arranges transport. Recruits staff and allocate work to them. Supervises and co-ordinates work of field and office staff. Keeps equipment, building, etc., in order. Maintains muster roll of labour and looks after office correspondence and keeps production and cost accounts. Pays various taxes and dues and fulfils other obligations. May specialize in growing certain types of crops. May conduct research and organize field demonstrations. May arrange preservation of crop. | Y95: =IF(COUNTA(E95:J95,P95:W95)=0,"Not started",IF(COUNTA(E95:J95,P95:W95)<14,"Incomplete",IF((AND(F95<>"",F95&""<>"0",TRIM(K95)="")+AND(G95<>"",G95&""<>"0",TRIM(L95)="")+AND(H95<>"",H95&""<>"0",TRIM(M95)="")+AND(I95<>"",I95&""<>"0",TRIM(N95)="")+AND(J95<>"",J95&""<>"0",TRIM(O95)=""))>0,"Add evidence","Complete"))) | Z95: 1311 | AA95: Agricultural and Forestry Production Managers | AB95: 131 | AC95: Production Managers in Agriculture, Forestry and Fisheries | AD95: 1 | AE95: Managers | AF95: Not defined | AG95: 1301.10
A96: 94 | B96: 1311.0400 | C96: General Manager, Livestock Farm | D96: General Manager, Livestock Farm manages livestock farm on behalf of the employer for breeding and raising different kinds of livestock. Arranges equipment and supplies for housing and feeding animals in consultation with employer. Selects and buys animals. Supervises preparation of feed, grazing arrangements and proper medical aid to keep animals in good health. Looks after pairing of animals on basis of pedigree for breeding. Supervises artificial insemination for developing good breed. Takes care of animals during birth of young and upbringing of young stock. Selects and sells animals for breeding and fieldwork. Disposes off unproductive and unprofitable animals to avoid wastage. Watches expenditure and receipts to ensure economic running of farm. Controls office and field staff and co-ordinates work. Maintains accounts and records details of feed consumed, milk and other items produced, purchase and sale of animals and other accounts relating to live-stock farm. May raise and exhibit show of animals. May supervise cultivation and raising of feed for animals. May specialize in any particular branch of livestock farming. May supervise work of Stockman. | Y96: =IF(COUNTA(E96:J96,P96:W96)=0,"Not started",IF(COUNTA(E96:J96,P96:W96)<14,"Incomplete",IF((AND(F96<>"",F96&""<>"0",TRIM(K96)="")+AND(G96<>"",G96&""<>"0",TRIM(L96)="")+AND(H96<>"",H96&""<>"0",TRIM(M96)="")+AND(I96<>"",I96&""<>"0",TRIM(N96)="")+AND(J96<>"",J96&""<>"0",TRIM(O96)=""))>0,"Add evidence","Complete"))) | Z96: 1311 | AA96: Agricultural and Forestry Production Managers | AB96: 131 | AC96: Production Managers in Agriculture, Forestry and Fisheries | AD96: 1 | AE96: Managers | AF96: Not defined | AG96: 1301.40
A97: 95 | B97: 1311.0500 | C97: General Manager, Dairy Farm | D97: General Manager, Dairy Farm manages dairy farm on behalf of employer for production of milk, butter, ghee, etc. Supervises selection and purchase of animals, in consultation with employer. Makes proper arrangements for housing, feeding and treatment of milking animals. Pairs animals for breeding on basis of pedigree. Arranges artificial insemination for developing good breed. Takes proper care of animals during birth of young and takes necessary precautions during upbringing of young animals. Ensures that hygienic methods are used in cleaning udder of animals, washing of hands of Milkman, milk containers, etc. before milking. Supervises milking, preparation of butter, ghee, etc. and arranges their transportation and marketing. Selects and sells unprofitable animals. Controls office and field staff and co-ordinates their work. | Y97: =IF(COUNTA(E97:J97,P97:W97)=0,"Not started",IF(COUNTA(E97:J97,P97:W97)<14,"Incomplete",IF((AND(F97<>"",F97&""<>"0",TRIM(K97)="")+AND(G97<>"",G97&""<>"0",TRIM(L97)="")+AND(H97<>"",H97&""<>"0",TRIM(M97)="")+AND(I97<>"",I97&""<>"0",TRIM(N97)="")+AND(J97<>"",J97&""<>"0",TRIM(O97)=""))>0,"Add evidence","Complete"))) | Z97: 1311 | AA97: Agricultural and Forestry Production Managers | AB97: 131 | AC97: Production Managers in Agriculture, Forestry and Fisheries | AD97: 1 | AE97: Managers | AF97: Not defined | AG97: 1301.50
A98: 96 | B98: 1311.0600 | C98: General Manager, Poultry | D98: General Manager, Poultry manages poultry farm on behalf of employer to raise poultry for eggs and table use and arranges sale of produce. Determines varieties of poultry to be raised in consultation with employer. Purchases feed, eggs, chicken, incubators and other equipment required for poultry farm. Supervises arrangements for feeding, breeding, hatching and construction of foster-mother pan, and brooder houses for housing newly born chicks and adult birds. Makes provision for proper sanitation and medical facilities and gets them vaccinated at proper age. Adopts labour saving devices, co-ordinates work of various sections and controls office staff. Implements plan carefully to achieve fixed target of production and yields profit. Takes preventive measures against diseases of birds. Isolates and treats or disposes off ailing birds and takes measures against spread of epidemics. Determines selling price for eggs of different grades and stock of different ages and pedigree. Keeps breeding record. Studies improved methods in poultry development. Arranges preservation of eggs during summer and disposal of poultry by-products. Undertakes measures to publicise products. Pays taxes and prepares profit and loss statements. Maintains all accounts and correspondence relating to the farm. May raise selected poultry and sell quality eggs for hatching. May arrange demonstration of various kinds of hatchery plants to develop hatching of eggs. May raise and exhibit show of stock. | Y98: =IF(COUNTA(E98:J98,P98:W98)=0,"Not started",IF(COUNTA(E98:J98,P98:W98)<14,"Incomplete",IF((AND(F98<>"",F98&""<>"0",TRIM(K98)="")+AND(G98<>"",G98&""<>"0",TRIM(L98)="")+AND(H98<>"",H98&""<>"0",TRIM(M98)="")+AND(I98<>"",I98&""<>"0",TRIM(N98)="")+AND(J98<>"",J98&""<>"0",TRIM(O98)=""))>0,"Add evidence","Complete"))) | Z98: 1311 | AA98: Agricultural and Forestry Production Managers | AB98: 131 | AC98: Production Managers in Agriculture, Forestry and Fisheries | AD98: 1 | AE98: Managers | AF98: Not defined | AG98: 1301.60
A99: 97 | B99: 1311.0700 | C99: Manager, Agricultural Farm | D99: Manager, Agriculture Farm; Superintendent, Agricultural Farm organizes and controls operations and staff employed in growing agricultural produce on large scale farm on behalf of Government or other employers. Determines crops to be grown after examining soil, irrigational facilities, climatic conditions and scope for marketing. Selects, purchases and stores seeds, fertilisers and agricultural implements. Organizes ,ploughing, manuring, sowing and watering. Devises ways and means to irrigate cultivation from well, tank, reservoir or other sources of water supply. Supervises operations of manure preparation, weeding, spraying insecticides and other measures to protect crops from wild animals, harvesting, threshing winnowing, bagging, storing etc. identifies markets for cultivated products and arranges transport. Recruits staff and allocates work to them. Supervises and co-ordinates work of field and office staff. Keeps equipment, building, etc., in order. Maintains muster roll of labour and looks after office correspondence and maintains production and cost accounts. Pays various taxes and dues and fulfils other obligations. May specialize in growing certain types of crops. May conduct research and organize field demonstrations. May arrange preservation of crop. | Y99: =IF(COUNTA(E99:J99,P99:W99)=0,"Not started",IF(COUNTA(E99:J99,P99:W99)<14,"Incomplete",IF((AND(F99<>"",F99&""<>"0",TRIM(K99)="")+AND(G99<>"",G99&""<>"0",TRIM(L99)="")+AND(H99<>"",H99&""<>"0",TRIM(M99)="")+AND(I99<>"",I99&""<>"0",TRIM(N99)="")+AND(J99<>"",J99&""<>"0",TRIM(O99)=""))>0,"Add evidence","Complete"))) | Z99: 1311 | AA99: Agricultural and Forestry Production Managers | AB99: 131 | AC99: Production Managers in Agriculture, Forestry and Fisheries | AD99: 1 | AE99: Managers | AF99: Not defined | AG99: 1221.10
A100: 98 | B100: 1311.0800 | C100: Manager, Plantation | D100: Manager, Plantation manages plantation on behalf of employer. Examines soil, climatic conditions, scope for marketing, etc. to determine type of crop such as tea, coffee, rubber etc. to be grown. Selects, purchases and stores seeds, fertilisers, agricultural implements, etc., as required. Organizes operation of ploughing, manuring, planting etc. Supervises operations of manure preparation, weeding, spraying insecticides and other measures to protect crops from wild animals and plant diseases. Organizes and supervises processes like tapping, threshing, plucking, withering, rolling, shifting, drying, cutting, sorting and storing of harvested produce. Undertakes publicity measures to publicise and to find out market for products and arranges for their transportation. Organizes and supervises construction of buildings, quarters, roads, tanks, installation of electric and telephone lines, etc. Supervises and co-ordinates work of field and office staff. Recruits staff and teaches them modern methods of plantation and allocates work. Keeps equipment, fences, building, etc. in order. Maintains muster roll of labour and looks after office correspondence. Looks after welfare of labour and ensures that provision of Plantation Act, Labour Act, etc. are maintained. Ensures proper payment to labour. Pays various taxes to Government and fulfils other obligations, if any. Maintains production and cost statements and submits periodical reports to proprietor. May specialize in growing particular types of plantation such as rubber, tea, coffee, etc. May conduct research and organize demonstration. May arrange preservation of produce. May partially process produce prior to marketing. | Y100: =IF(COUNTA(E100:J100,P100:W100)=0,"Not started",IF(COUNTA(E100:J100,P100:W100)<14,"Incomplete",IF((AND(F100<>"",F100&""<>"0",TRIM(K100)="")+AND(G100<>"",G100&""<>"0",TRIM(L100)="")+AND(H100<>"",H100&""<>"0",TRIM(M100)="")+AND(I100<>"",I100&""<>"0",TRIM(N100)="")+AND(J100<>"",J100&""<>"0",TRIM(O100)=""))>0,"Add evidence","Complete"))) | Z100: 1311 | AA100: Agricultural and Forestry Production Managers | AB100: 131 | AC100: Production Managers in Agriculture, Forestry and Fisheries | AD100: 1 | AE100: Managers | AF100: Not defined | AG100: 1221.20
A101: 99 | B101: 1311.0900 | C101: Manager, Nursery | D101: Manager, Nursery manages nursery to grow horticultural plants, such as trees, shrubs, flowers, ornamental plants, or vegetables for sale to trade or retail customers: Determines type and quantity of horticultural plants to be grown, considering such factors as whether plants will be grown under controlled conditions in hothouse or greenhouse or under natural weather conditions in field, and market demand or conditions, utilizing knowledge of plant germination, growing habits of plants, soil conditions, plant nutrients, and disease control requirements. Selects and purchases seed, plant nutrients, and disease control chemicals according to type of horticultural plants and conditions under which plants will be grown. Tours work areas to observe quality and quantity of work being done, to inspect crops and to evaluate horticultural conditions, such as plant disease and soil conditions. Directs and co-ordinates, through subordinate supervisory personnel, activities of workers engaged in planting of seed, raising, feeding, and controlling growth and disease of plants, and transplanting, potting, or cutting plants for marketing. Co-ordinates clerical, record keeping, accounting and marketing activities. May purchase nursery stock for resale and sell gardening accessories, such as sprays, garden implements and plant nutrients. | Y101: =IF(COUNTA(E101:J101,P101:W101)=0,"Not started",IF(COUNTA(E101:J101,P101:W101)<14,"Incomplete",IF((AND(F101<>"",F101&""<>"0",TRIM(K101)="")+AND(G101<>"",G101&""<>"0",TRIM(L101)="")+AND(H101<>"",H101&""<>"0",TRIM(M101)="")+AND(I101<>"",I101&""<>"0",TRIM(N101)="")+AND(J101<>"",J101&""<>"0",TRIM(O101)=""))>0,"Add evidence","Complete"))) | Z101: 1311 | AA101: Agricultural and Forestry Production Managers | AB101: 131 | AC101: Production Managers in Agriculture, Forestry and Fisheries | AD101: 1 | AE101: Managers | AF101: Not defined | AG101: 1221.22
A102: 100 | B102: 1311.0901 | C102: Rubber Nursery Manager | D102: Rubber Nursery Manager controls and co-ordinates all the nursery activities, labour management and office work. He is responsible for the quality assurance of the planting materials produced from the nursery. | Y102: =IF(COUNTA(E102:J102,P102:W102)=0,"Not started",IF(COUNTA(E102:J102,P102:W102)<14,"Incomplete",IF((AND(F102<>"",F102&""<>"0",TRIM(K102)="")+AND(G102<>"",G102&""<>"0",TRIM(L102)="")+AND(H102<>"",H102&""<>"0",TRIM(M102)="")+AND(I102<>"",I102&""<>"0",TRIM(N102)="")+AND(J102<>"",J102&""<>"0",TRIM(O102)=""))>0,"Add evidence","Complete"))) | Z102: 1311 | AA102: Agricultural and Forestry Production Managers | AB102: 131 | AC102: Production Managers in Agriculture, Forestry and Fisheries | AD102: 1 | AE102: Managers | AF102: Not defined | AH102: RSC/Q0932
A103: 101 | B103: 1311.1000 | C103: Manager, Aerial Planting and Cultivation | D103: Manager, Aerial Planting and Cultivation manages operations of aerial seed sowing and crop dusting establishment. Negotiates contracts with farm personnel to sow seeds of specified varieties or to spray or dust fields or crops with specified agricultural chemicals. Confers with the required authority to determine materials and conditions required to meet terms of contract and schedules flights according to factors, such as client requests, weather conditions, aircraft availability, and legal and safety considerations. Monitors mixing of chemicals, loading chemicals and seeds into hopper of aircraft, and indicates flight passes to pilots from ground to ensure efficient and safe operations. Purchases seeds and chemicals from suppliers. Oversees repair and maintenance of aircraft and contracts for repair and maintenance of hangars, runway, and related company facilities. Maintains records for billing and payroll purposes. Initiates personnel actions, such as hiring, firing, and disciplining workers. | Y103: =IF(COUNTA(E103:J103,P103:W103)=0,"Not started",IF(COUNTA(E103:J103,P103:W103)<14,"Incomplete",IF((AND(F103<>"",F103&""<>"0",TRIM(K103)="")+AND(G103<>"",G103&""<>"0",TRIM(L103)="")+AND(H103<>"",H103&""<>"0",TRIM(M103)="")+AND(I103<>"",I103&""<>"0",TRIM(N103)="")+AND(J103<>"",J103&""<>"0",TRIM(O103)=""))>0,"Add evidence","Complete"))) | Z103: 1311 | AA103: Agricultural and Forestry Production Managers | AB103: 131 | AC103: Production Managers in Agriculture, Forestry and Fisheries | AD103: 1 | AE103: Managers | AF103: Not defined | AG103: 1221.24
A104: 102 | B104: 1311.1100 | C104: Manager, Orchard | D104: Manager, Orchard manages orchards: Directs and co-ordinates, through subordinate supervisory personnel, orchard activities, such as orchard development, irrigation, chemical application and harvesting to ensure that company production goals are met. Evaluates oral and written reports and observes operations to monitor progress of work and to detect and resolve problems. Determines and authorizes alternative procedures to accommodate variables, such as weather conditions, water supply, stage of crops or tree development, and new legislation. Co-ordinates activities of the orchard department with those of engineering, equipment maintenance, packing house, and other related departments. Analyses financial statements and makes budget proposals. May initiate personnel actions, interpret company policies, and enforce safety regulations | Y104: =IF(COUNTA(E104:J104,P104:W104)=0,"Not started",IF(COUNTA(E104:J104,P104:W104)<14,"Incomplete",IF((AND(F104<>"",F104&""<>"0",TRIM(K104)="")+AND(G104<>"",G104&""<>"0",TRIM(L104)="")+AND(H104<>"",H104&""<>"0",TRIM(M104)="")+AND(I104<>"",I104&""<>"0",TRIM(N104)="")+AND(J104<>"",J104&""<>"0",TRIM(O104)=""))>0,"Add evidence","Complete"))) | Z104: 1311 | AA104: Agricultural and Forestry Production Managers | AB104: 131 | AC104: Production Managers in Agriculture, Forestry and Fisheries | AD104: 1 | AE104: Managers | AF104: Not defined | AG104: 1221.26
A105: 103 | B105: 1311.1200 | C105: Manager, Horticulture Farm | D105: Manager, Horticulture Farm organizes and supervises planting, maintenance and growth of fruit plants and arranges for marketing of produce. Determines types of fruits or nuts to be grown depending on the nature of soil and climate, irrigation and market facilities. Selects and purchases plants, fertilisers and agricultural implements. Organizes operations of ploughing, manuring, sowing or planting and watering. Devises ways and means to supply regular flow of water for irrigation. Supervises agricultural operations, such as weeding, spraying insecticides, manuring and harvesting. Selects the best market for produce and arranges its transportation. Supervises and controls field and office staff. Trains field workers in latest methods of grafting and planting of trees. Attends to office correspondence and maintains cost and production accounts. Keeps equipment and building, etc. in good order. Pays various taxes and dues and fulfils other obligations. May specialize in growing particular types of fruits. May conduct research and organize field demonstration. May arrange preservation of fruits by canning or in cold storage. May develop variety of fruit trees by grafting and budding. | Y105: =IF(COUNTA(E105:J105,P105:W105)=0,"Not started",IF(COUNTA(E105:J105,P105:W105)<14,"Incomplete",IF((AND(F105<>"",F105&""<>"0",TRIM(K105)="")+AND(G105<>"",G105&""<>"0",TRIM(L105)="")+AND(H105<>"",H105&""<>"0",TRIM(M105)="")+AND(I105<>"",I105&""<>"0",TRIM(N105)="")+AND(J105<>"",J105&""<>"0",TRIM(O105)=""))>0,"Add evidence","Complete"))) | Z105: 1311 | AA105: Agricultural and Forestry Production Managers | AB105: 131 | AC105: Production Managers in Agriculture, Forestry and Fisheries | AD105: 1 | AE105: Managers | AF105: Not defined | AG105: 1221.30
A106: 104 | B106: 1311.1300 | C106: Manager, Livestock Farm | D106: Manager, Livestock Farm manages a live-stock farm on behalf of the employer for breeding and raising different kinds of live-stock. Arranges equipment and supplies for housing and feeding animals in consultation with the employer. Selects and buys animals. Supervises preparation of feed, grazing arrangements and proper medical aid to keep animals in good health. Looks after pairing of animals on the basis of pedigree for breeding. Supervises artificial insemination for developing good breed. Takes care of animals during birth of young and upbringing of young stock. Selects and sells animals for breeding and field work. Disposes off unproductive and unprofitable animals to avoid wastage. Watches expenditure and receipts to ensure economic running of the farm. Controls office and field staff and co-ordinates work. Maintains accounts and records details of feed consumed, milk and other items produced, purchase and sale of animals and other accounts relating to the live-stock farm. May raise and exhibit show animals. May supervise cultivation and raising of feed for animals. May specialise in any particular branch of live-stock farming. May supervise work of Stockman. | Y106: =IF(COUNTA(E106:J106,P106:W106)=0,"Not started",IF(COUNTA(E106:J106,P106:W106)<14,"Incomplete",IF((AND(F106<>"",F106&""<>"0",TRIM(K106)="")+AND(G106<>"",G106&""<>"0",TRIM(L106)="")+AND(H106<>"",H106&""<>"0",TRIM(M106)="")+AND(I106<>"",I106&""<>"0",TRIM(N106)="")+AND(J106<>"",J106&""<>"0",TRIM(O106)=""))>0,"Add evidence","Complete"))) | Z106: 1311 | AA106: Agricultural and Forestry Production Managers | AB106: 131 | AC106: Production Managers in Agriculture, Forestry and Fisheries | AD106: 1 | AE106: Managers | AF106: Not defined | AG106: 1221.40
A107: 105 | B107: 1311.1400 | C107: Manager, Dairy Farm | D107: Manager, Dairy Farm manages a dairy farm on behalf of the employer for production of milk, butter, ghee, etc. Supervises selection and purchase of animals, in consultation with the employer. Makes proper arrangements for housing, feeding and treatment of milking animals. Pairs animals for breeding on basis of pedigree. Arranges artificial insemination for developing good breed. Takes proper care of animals during birth of young and takes necessary precautions during upbringing of young animals. Ensures that hygienic methods are maintained while cleaning udder of animals, washing hands of Milkman, milk containers, etc. before milking. Supervises milking, preparation of butter, ghee, etc. and arranges their transportation and marketing. Selects and sells unprofitable animals. Controls office and field staff and co-ordinates their work. Records details of feed consumed, milk and other produce, purchase and sale of animals and other items relating to the income and expenditure of the dairy. Avoids wastage, maintains proper accounts and watches expenditure and receipts of farm for economic consideration. May raise and exhibit show animals. May arrange and supervise production of feed for animals. May conduct research and demonstrate process of working. | Y107: =IF(COUNTA(E107:J107,P107:W107)=0,"Not started",IF(COUNTA(E107:J107,P107:W107)<14,"Incomplete",IF((AND(F107<>"",F107&""<>"0",TRIM(K107)="")+AND(G107<>"",G107&""<>"0",TRIM(L107)="")+AND(H107<>"",H107&""<>"0",TRIM(M107)="")+AND(I107<>"",I107&""<>"0",TRIM(N107)="")+AND(J107<>"",J107&""<>"0",TRIM(O107)=""))>0,"Add evidence","Complete"))) | Z107: 1311 | AA107: Agricultural and Forestry Production Managers | AB107: 131 | AC107: Production Managers in Agriculture, Forestry and Fisheries | AD107: 1 | AE107: Managers | AF107: Not defined | AG107: 1221.50
A108: 106 | B108: 1311.1500 | C108: Manager, Poultry Farm | D108: Manager, Poultry Farm manages a poultry farm on behalf of the employer to raise poultry for eggs and table use and arranges sale of produce. Determines varieties of poultry to be raised in consultation with the employer. Purchases feed, eggs, chicken, incubators and other equipment required for the poultry farm. Supervises arrangements for feeding, breeding, hatching and construction of foster-mother, pan, and brooder houses for housing newly born chicks and adult birds. Makes provision for proper sanitation and medical facilities and gets them vaccinated at a proper age. Adopts labour saving devices, co-ordinates work of various sections and controls office staff. Implements plans carefully to achieve fixed target of production and yield profit. Takes preventive measures against diseases of birds. Isolates and treats or disposes off ailing birds and takes measures against the spread of epidemics. Determines selling price for eggs of different grades and stock of different ages and pedigree. Maintains breeding record. Studies improved methods in poultry development. Arranges preservation of eggs during summer and disposal of poultry by-products. Undertakes measures to publicise products. Maintains all accounts and correspondence relating to the farm. May raise selected poultry and sell quality eggs for hatching. May arrange demonstration of various kinds of hatchery plants to develop hatching of eggs. May raise and exhibit show stock. | Y108: =IF(COUNTA(E108:J108,P108:W108)=0,"Not started",IF(COUNTA(E108:J108,P108:W108)<14,"Incomplete",IF((AND(F108<>"",F108&""<>"0",TRIM(K108)="")+AND(G108<>"",G108&""<>"0",TRIM(L108)="")+AND(H108<>"",H108&""<>"0",TRIM(M108)="")+AND(I108<>"",I108&""<>"0",TRIM(N108)="")+AND(J108<>"",J108&""<>"0",TRIM(O108)=""))>0,"Add evidence","Complete"))) | Z108: 1311 | AA108: Agricultural and Forestry Production Managers | AB108: 131 | AC108: Production Managers in Agriculture, Forestry and Fisheries | AD108: 1 | AE108: Managers | AF108: Not defined | AG108: 1221.60
A109: 107 | B109: 1311.9900 | C109: Agricultural and Forestry Production Managers, Others | D109: Agricultural and Forestry Production Managers, Others include all other Farm Managers and supervisors engaged in agriculture, horticulture, poultry, dairy, livestock and farming, not elsewhere classified. | Y109: =IF(COUNTA(E109:J109,P109:W109)=0,"Not started",IF(COUNTA(E109:J109,P109:W109)<14,"Incomplete",IF((AND(F109<>"",F109&""<>"0",TRIM(K109)="")+AND(G109<>"",G109&""<>"0",TRIM(L109)="")+AND(H109<>"",H109&""<>"0",TRIM(M109)="")+AND(I109<>"",I109&""<>"0",TRIM(N109)="")+AND(J109<>"",J109&""<>"0",TRIM(O109)=""))>0,"Add evidence","Complete"))) | Z109: 1311 | AA109: Agricultural and Forestry Production Managers | AB109: 131 | AC109: Production Managers in Agriculture, Forestry and Fisheries | AD109: 1 | AE109: Managers | AF109: Not defined | AG109: 1221.90
A110: 108 | B110: 1321.0100 | C110: Manager, Electricity | D110: Manager, Electricity co-ordinates and supervises, within authority delegated efficient utilisation of men, money and material in public or private organizations or establishments, or one or more of its departments, branches, etc., engaged in generation, transmission and distribution of electricity to domestic and industrial consumers | Y110: =IF(COUNTA(E110:J110,P110:W110)=0,"Not started",IF(COUNTA(E110:J110,P110:W110)<14,"Incomplete",IF((AND(F110<>"",F110&""<>"0",TRIM(K110)="")+AND(G110<>"",G110&""<>"0",TRIM(L110)="")+AND(H110<>"",H110&""<>"0",TRIM(M110)="")+AND(I110<>"",I110&""<>"0",TRIM(N110)="")+AND(J110<>"",J110&""<>"0",TRIM(O110)=""))>0,"Add evidence","Complete"))) | Z110: 1321 | AA110: Manufacturing Managers | AB110: 132 | AC110: Manufacturing, Mining, Construction and Distribution Managers | AD110: 1 | AE110: Managers | AF110: Not defined | AG110: 1222.40
A111: 109 | B111: 1321.0200 | C111: Terminal Manager | D111: Terminal Manager/Terminal Superintendent manages plants in which Liquefied Petroleum Gas, lubricants, and petroleum fuels are stored and distributed in bulk. Formulates policies with regard to storage, distribution and other operating problems. Determines type and quantities of products according to consumer demand. Contacts refineries and petroleum canning plants to schedule shipment of products. Establishes operating procedures for incoming shipments, indicating storage tanks and warehouse facilities to be used. Formulates policies for distribution and sale of products to wholesale and retail outlets and consumers. | Y111: =IF(COUNTA(E111:J111,P111:W111)=0,"Not started",IF(COUNTA(E111:J111,P111:W111)<14,"Incomplete",IF((AND(F111<>"",F111&""<>"0",TRIM(K111)="")+AND(G111<>"",G111&""<>"0",TRIM(L111)="")+AND(H111<>"",H111&""<>"0",TRIM(M111)="")+AND(I111<>"",I111&""<>"0",TRIM(N111)="")+AND(J111<>"",J111&""<>"0",TRIM(O111)=""))>0,"Add evidence","Complete"))) | Z111: 1321 | AA111: Manufacturing Managers | AB111: 132 | AC111: Manufacturing, Mining, Construction and Distribution Managers | AD111: 1 | AE111: Managers | AF111: Not defined | AG111: 1222.45
A112: 110 | B112: 1321.0300 | C112: Manager, Gas | D112: Manager, Gas co-ordinates and controls, within authority delegated, efficient utilization of men, money and material in public or private organizations or establishments, or one or more of its departments, sections or branches, engaged in manufacture of gas and distribution of manufactured or natural gas to consumers, and production and supply of steam for heat, power, etc. | Y112: =IF(COUNTA(E112:J112,P112:W112)=0,"Not started",IF(COUNTA(E112:J112,P112:W112)<14,"Incomplete",IF((AND(F112<>"",F112&""<>"0",TRIM(K112)="")+AND(G112<>"",G112&""<>"0",TRIM(L112)="")+AND(H112<>"",H112&""<>"0",TRIM(M112)="")+AND(I112<>"",I112&""<>"0",TRIM(N112)="")+AND(J112<>"",J112&""<>"0",TRIM(O112)=""))>0,"Add evidence","Complete"))) | Z112: 1321 | AA112: Manufacturing Managers | AB112: 132 | AC112: Manufacturing, Mining, Construction and Distribution Managers | AD112: 1 | AE112: Managers | AF112: Not defined | AG112: 1222.50
A113: 111 | B113: 1321.0400 | C113: Manager, Water Supply | D113: Manager, Water Supply co-ordinates and supervises within powers delegated, efficient utilisation of men, money and material in public or private organizations, or one or more of its departments or branches, engaged in storing, filtering and purifying water and supplying water to consumers. | Y113: =IF(COUNTA(E113:J113,P113:W113)=0,"Not started",IF(COUNTA(E113:J113,P113:W113)<14,"Incomplete",IF((AND(F113<>"",F113&""<>"0",TRIM(K113)="")+AND(G113<>"",G113&""<>"0",TRIM(L113)="")+AND(H113<>"",H113&""<>"0",TRIM(M113)="")+AND(I113<>"",I113&""<>"0",TRIM(N113)="")+AND(J113<>"",J113&""<>"0",TRIM(O113)=""))>0,"Add evidence","Complete"))) | Z113: 1321 | AA113: Manufacturing Managers | AB113: 132 | AC113: Manufacturing, Mining, Construction and Distribution Managers | AD113: 1 | AE113: Managers | AF113: Not defined | AG113: 1222.60
A114: 112 | B114: 1321.0500 | C114: Manager, Food Processing Plant | D114: Manager food processing plant directs and co-ordinates activities of food processing plants. Contacts buyers or growers to arrange for purchasing or harvesting and delivery of agricultural products, seafood, meat, or other raw materials to plant for processing. Directs, through subordinate supervisory personnel, workers engaged in processing, canning, freezing, storing, and shipping food products. Directs and co-ordinates activities concerned with dismantling, moving, installing, or repair of machines and equipment. Approves plant payroll and payments for purchased materials or products. Estimates quantities of foods for processing required and orders foods, materials, supplies, and equipment needed. Hires, transfers, and discharges employees. May provide suppliers with transportation to expedite delivery of purchased products or supplies to the plant. May arrange for freezing of packaged products by other food processing plants. May negotiate with suppliers or growers regarding prices to be paid for purchases. | Y114: =IF(COUNTA(E114:J114,P114:W114)=0,"Not started",IF(COUNTA(E114:J114,P114:W114)<14,"Incomplete",IF((AND(F114<>"",F114&""<>"0",TRIM(K114)="")+AND(G114<>"",G114&""<>"0",TRIM(L114)="")+AND(H114<>"",H114&""<>"0",TRIM(M114)="")+AND(I114<>"",I114&""<>"0",TRIM(N114)="")+AND(J114<>"",J114&""<>"0",TRIM(O114)=""))>0,"Add evidence","Complete"))) | Z114: 1321 | AA114: Manufacturing Managers | AB114: 132 | AC114: Manufacturing, Mining, Construction and Distribution Managers | AD114: 1 | AE114: Managers | AF114: Not defined | AG114: 1222.65
... A132: 130 | B132: 1324.0100 | C132: Manager, Material Control/Manager Materials | D132: Manager, Material Control directs and co-ordinates activities of personnel engaged in purchasing and distributing raw materials, equipment, machinery, and supplies in industrial plants, public utilities, or other organizations: Prepares instructions regarding purchasing systems and procedures. Prepares and issues purchase orders and submits notices to Purchasing Agents. Analyses market and delivery conditions to determine present and future material availability and prepares market analysis reports. Reviews purchase order claims and contracts for conformance to company policy. Develops and installs clerical and office procedures and practices, and studies work flow, sequence of operations, and office arrangement to determine expediency of installing new or improved office machines. Arranges for disposal of surplus materials. | Y132: =IF(COUNTA(E132:J132,P132:W132)=0,"Not started",IF(COUNTA(E132:J132,P132:W132)<14,"Incomplete",IF((AND(F132<>"",F132&""<>"0",TRIM(K132)="")+AND(G132<>"",G132&""<>"0",TRIM(L132)="")+AND(H132<>"",H132&""<>"0",TRIM(M132)="")+AND(I132<>"",I132&""<>"0",TRIM(N132)="")+AND(J132<>"",J132&""<>"0",TRIM(O132)=""))>0,"Add evidence","Complete"))) | Z132: 1324 | AA132: Supply, Distribution and Related Managers | AB132: 132 | AC132: Manufacturing, Mining, Construction and Distribution Managers | AD132: 1 | AE132: Managers | AF132: Not defined | AG132: 1235.10
A133: 131 | B133: 1324.0101 | C133: Manager Supplier Quality | D133: Manager Supplier Quality needs to be responsible for overall supplier quality assurance functions for all facilities including incoming inspection, issue containment and supplier corrective actions. | Y133: =IF(COUNTA(E133:J133,P133:W133)=0,"Not started",IF(COUNTA(E133:J133,P133:W133)<14,"Incomplete",IF((AND(F133<>"",F133&""<>"0",TRIM(K133)="")+AND(G133<>"",G133&""<>"0",TRIM(L133)="")+AND(H133<>"",H133&""<>"0",TRIM(M133)="")+AND(I133<>"",I133&""<>"0",TRIM(N133)="")+AND(J133<>"",J133&""<>"0",TRIM(O133)=""))>0,"Add evidence","Complete"))) | Z133: 1324 | AA133: Supply, Distribution and Related Managers | AB133: 132 | AC133: Manufacturing, Mining, Construction and Distribution Managers | AD133: 1 | AE133: Managers | AF133: Not defined | AH133: ASC/Q6302
A134: 132 | B134: 1324.0102 | C134: Material Co-ordination Manager | D134: Material Co-ordination Manager needs to co-ordinate and expedite procurement and flow of materials, parts, and assemblies between sections or departments of manufacturing, according to production and shipping schedules to ensure timely production of goods | Y134: =IF(COUNTA(E134:J134,P134:W134)=0,"Not started",IF(COUNTA(E134:J134,P134:W134)<14,"Incomplete",IF((AND(F134<>"",F134&""<>"0",TRIM(K134)="")+AND(G134<>"",G134&""<>"0",TRIM(L134)="")+AND(H134<>"",H134&""<>"0",TRIM(M134)="")+AND(I134<>"",I134&""<>"0",TRIM(N134)="")+AND(J134<>"",J134&""<>"0",TRIM(O134)=""))>0,"Add evidence","Complete"))) | Z134: 1324 | AA134: Supply, Distribution and Related Managers | AB134: 132 | AC134: Manufacturing, Mining, Construction and Distribution Managers | AD134: 1 | AE134: Managers | AF134: Not defined | AH134: ASC/Q6105
A135: 133 | B135: 1324.0103 | C135: Manager Vendor Development | D135: Manager Vendor Development needs to co-ordinate and expedite procurement and flow of materials, parts, and assemblies between sections or departments of manufacturing, according to production and shipping schedules to ensure timely production of goods. | Y135: =IF(COUNTA(E135:J135,P135:W135)=0,"Not started",IF(COUNTA(E135:J135,P135:W135)<14,"Incomplete",IF((AND(F135<>"",F135&""<>"0",TRIM(K135)="")+AND(G135<>"",G135&""<>"0",TRIM(L135)="")+AND(H135<>"",H135&""<>"0",TRIM(M135)="")+AND(I135<>"",I135&""<>"0",TRIM(N135)="")+AND(J135<>"",J135&""<>"0",TRIM(O135)=""))>0,"Add evidence","Complete"))) | Z135: 1324 | AA135: Supply, Distribution and Related Managers | AB135: 132 | AC135: Manufacturing, Mining, Construction and Distribution Managers | AD135: 1 | AE135: Managers | AF135: Not defined | AH135: ASC/Q6203
A136: 134 | B136: 1324.0200 | C136: Manager, Transport | D136: Manager, Transport supervises co-ordinates and controls, within authority delegated, efficient utilisation of men, money and material in public or private organizations or establishments, or one or more of its departments, branches or sections, engaged in transporting passengers and freight by railways, tramways, buses, trucks, taxis, rickshaws, boats, launches, ships, aircrafts and other means of transport, and operating services incidental to transport. Is designated according to work performed, authority exercised or transport service supervised such as: DIVISIONAL SUPERINTENDENT (RAILWAY),TRAFFIC SUPERINTENDENT(RAILWAY). COMMERCIAL SUPERINTENDENT(RAILWAY). STATION SUPERINTENDENT(RAILWAY). MANAGER, ROAD TRANSPORT, TRAFFIC MANAGER, MOTOR TRANSPORT, MANAGER, ROADWAYS, MANAGER, TAXI SERVICE, MANAGER, AIRLINES, AREA MANAGER, AIRLINES, TRAFFIC MANAGER, AIRLINES, OPERATING MANAGER, AIRLINES, MANAGER, SHIPPING, MANAGER, DOCK. | Y136: =IF(COUNTA(E136:J136,P136:W136)=0,"Not started",IF(COUNTA(E136:J136,P136:W136)<14,"Incomplete",IF((AND(F136<>"",F136&""<>"0",TRIM(K136)="")+AND(G136<>"",G136&""<>"0",TRIM(L136)="")+AND(H136<>"",H136&""<>"0",TRIM(M136)="")+AND(I136<>"",I136&""<>"0",TRIM(N136)="")+AND(J136<>"",J136&""<>"0",TRIM(O136)=""))>0,"Add evidence","Complete"))) | Z136: 1324 | AA136: Supply, Distribution and Related Managers | AB136: 132 | AC136: Manufacturing, Mining, Construction and Distribution Managers | AD136: 1 | AE136: Managers | AF136: Not defined | AG136: 1226.10
A137: 135 | B137: 1324.0300 | C137: Station Master, Roadways | D137: Station Master, Roadways controls and co-ordinates work of staff employed at roadways' stations, and supervises operation of all passenger buses, cars, luggage vans, and goods trucks within his section. Arranges layout of roadways' station for parking of vehicles, signboards of routes, scheduled timings of incoming and outgoing vehicles, passenger waiting hall, booking office counters, etc. for orderly conduct of business. Displays time and fare table and other important notices in station premises. Provides passenger amenities such as drinking water, and other conveniences for passengers. Prepares duty roster of Bus Conductors, Drivers and Cleaners. Checks attendance of staff under him and supervises their work. Maintains check sheets of all incoming and outgoing vehicles, their number, station from where arrived, destination, time of arrival and departure etc. to ensure regularity and punctuality of service. Maintains fuel records issued to vehicles and checks way bills and journey bills of Conductors to verify correctness of fuel consumption, passenger fare and freight charge collections. Ensures that parcels and luggage’s offered for transport by bus van and truck are packed, labelled and addressed properly. Arranges for running of additional buses to relieve heavy traffic of passengers in time of mela and important occasions. Rushes relief buses and other assistance in case of break down and accident. Attends to passenger complaints and takes re-medial action by reporting to proper authority as case merits. Maintains necessary records and registers, submits return as prescribed and performs other duties to promote road transport. Checks malpractices, ensures safety of passengers and goods booked, cleanliness of premises and incoming and outgoing buses, convenience of passengers, etc. May check passengers' tickets en route within his jurisdiction. | Y137: =IF(COUNTA(E137:J137,P137:W137)=0,"Not started",IF(COUNTA(E137:J137,P137:W137)<14,"Incomplete",IF((AND(F137<>"",F137&""<>"0",TRIM(K137)="")+AND(G137<>"",G137&""<>"0",TRIM(L137)="")+AND(H137<>"",H137&""<>"0",TRIM(M137)="")+AND(I137<>"",I137&""<>"0",TRIM(N137)="")+AND(J137<>"",J137&""<>"0",TRIM(O137)=""))>0,"Add evidence","Complete"))) | Z137: 1324 | AA137: Supply, Distribution and Related Managers | AB137: 132 | AC137: Manufacturing, Mining, Construction and Distribution Managers | AD137: 1 | AE137: Managers | AF137: Not defined | AG137: 1226.15
A138: 136 | B138: 1324.0400 | C138: Traffic Inspector, Motor Transport | D138: Traffic Inspector, Motor Transport inspects buses running on any route or area allotted to him and supervises work of Ticket Examiners, Time Keepers, Bus Conductors and Bus Drivers. Checks general appearance of buses and whether Conductors and Drivers are in uniform. Checks whether buses are running at scheduled timings. Examines tickets and luggage of passengers to see whether correct tickets have been issued, and properly punched. Supervises alighting and boarding of passengers at important stops or destinations. Regulates arrival, departure and frequency of buses at important stops. Arranges for running of extra buses in cases of heavy rush of traffic. Visits spot in case of accidents, obtains facts and evidence thereof, etc. Informs nearest police station, gets in touch with depot or headquarters and submits reports to higher authorities. Diverts buses to alternate routes within city in case of fire, breakdown, jam, etc. Studies traffic requirements within his area, offers suggestions regarding timings, frequency, introduction or curtailment of services, and communicates reaction of passengers to management for appropriate action. May be designated as CHIEF INSPECTOR. MOTOR TRANSPORT if also engaged in supervising work of other MOTOR TRANSPORT INSPECTORS. | Y138: =IF(COUNTA(E138:J138,P138:W138)=0,"Not started",IF(COUNTA(E138:J138,P138:W138)<14,"Incomplete",IF((AND(F138<>"",F138&""<>"0",TRIM(K138)="")+AND(G138<>"",G138&""<>"0",TRIM(L138)="")+AND(H138<>"",H138&""<>"0",TRIM(M138)="")+AND(I138<>"",I138&""<>"0",TRIM(N138)="")+AND(J138<>"",J138&""<>"0",TRIM(O138)=""))>0,"Add evidence","Complete"))) | Z138: 1324 | AA138: Supply, Distribution and Related Managers | AB138: 132 | AC138: Manufacturing, Mining, Construction and Distribution Managers | AD138: 1 | AE138: Managers | AF138: Not defined | AG138: 1226.17
A139: 137 | B139: 1324.0500 | C139: Manager, Traffic | D139: Manager, Traffic conducts studies on company freight and passenger classifications, rates, and tariffs and formulates changes required to provide for increased revenues and profitability of operations: Analyses financial reports on operations and evaluates existing classifications, rates, and tariffs to determine changes required and need for expansion or curtailment of schedules and routes. Documents data to support proposals for increased revenues, expansion of schedules or routes, and files application for new rates, schedules, or routes with regulatory agencies. Testifies before regulatory agencies to present company's position and need for increased revenues in order to operate profitability. Negotiates with personnel of other transportation companies on division of interline revenues and signs contract on terms of agreement. Consults with officials of other companies on traffic movement problems, such as freight handling, transfer, and in-transit storage. Directs and co-ordinates activities of workers in classification of shipments and in applying and enforcing rates and tariffs. | Y139: =IF(COUNTA(E139:J139,P139:W139)=0,"Not started",IF(COUNTA(E139:J139,P139:W139)<14,"Incomplete",IF((AND(F139<>"",F139&""<>"0",TRIM(K139)="")+AND(G139<>"",G139&""<>"0",TRIM(L139)="")+AND(H139<>"",H139&""<>"0",TRIM(M139)="")+AND(I139<>"",I139&""<>"0",TRIM(N139)="")+AND(J139<>"",J139&""<>"0",TRIM(O139)=""))>0,"Add evidence","Complete"))) | Z139: 1324 | AA139: Supply, Distribution and Related Managers | AB139: 132 | AC139: Manufacturing, Mining, Construction and Distribution Managers | AD139: 1 | AE139: Managers | AF139: Not defined | AG139: 1226.20
A140: 138 | B140: 1324.0600 | C140: Traffic Inspector, Railway | D140: Traffic Inspector, Railway inspects activities of stations under his jurisdiction to ensure compliance of all traffic and operative rules. Examines records and registers maintained at each station to check attendance records and efficiency of staff and extent to which trains operate on schedule. Inspects condition of station building, platform, drinking-water, refreshment facilities and other public conveniences. Checks crossing gates, goods shed, and parcel office for compliance with safety regulations. Conducts night inspection of signals and ensures that lighting arrangements are adequate. Makes surprise inspections by travelling in passenger or goods trains to check compliance with traffic rules. Accompanies important passengers in train to ensure that all facilities and courtesies are provided to them. Resolves public complaints and investigates minor accidents, theft of goods, delays, etc. | Y140: =IF(COUNTA(E140:J140,P140:W140)=0,"Not started",IF(COUNTA(E140:J140,P140:W140)<14,"Incomplete",IF((AND(F140<>"",F140&""<>"0",TRIM(K140)="")+AND(G140<>"",G140&""<>"0",TRIM(L140)="")+AND(H140<>"",H140&""<>"0",TRIM(M140)="")+AND(I140<>"",I140&""<>"0",TRIM(N140)="")+AND(J140<>"",J140&""<>"0",TRIM(O140)=""))>0,"Add evidence","Complete"))) | Z140: 1324 | AA140: Supply, Distribution and Related Managers | AB140: 132 | AC140: Manufacturing, Mining, Construction and Distribution Managers | AD140: 1 | AE140: Managers | AF140: Not defined | AG140: 1226.25
A141: 139 | B141: 1324.0700 | C141: Traffic Inspector, Tram | D141: Traffic Inspector Tram supervises work of Tram Conductors and Tram Car Drivers to ensure operation of trams on schedule. Substitutes temporarily for Tram Starter. Checks Conductor's memo by field inspection to ensure running of tram at scheduled time. Tallies tickets sold with recorded entry and tickets held by passengers travelling in trams to check and avoid over payment of fares or over travelling by passengers. Reports complaints of poor service to higher authorities for action. Visits accident or breakdown sites and arranges to clear line to restore normal traffic. Provides first aid to injured persons. Observes performance of Conductors and reports any irregularity noticed to higher authorities. Maintains statistics of passengers travelling in tram cars and suggests improvement in schedule to divisional authorities. | Y141: =IF(COUNTA(E141:J141,P141:W141)=0,"Not started",IF(COUNTA(E141:J141,P141:W141)<14,"Incomplete",IF((AND(F141<>"",F141&""<>"0",TRIM(K141)="")+AND(G141<>"",G141&""<>"0",TRIM(L141)="")+AND(H141<>"",H141&""<>"0",TRIM(M141)="")+AND(I141<>"",I141&""<>"0",TRIM(N141)="")+AND(J141<>"",J141&""<>"0",TRIM(O141)=""))>0,"Add evidence","Complete"))) | Z141: 1324 | AA141: Supply, Distribution and Related Managers | AB141: 132 | AC141: Manufacturing, Mining, Construction and Distribution Managers | AD141: 1 | AE141: Managers | AF141: Not defined | AG141: 1226.29
...

Sheet Progress
A1: Coding progress
A2: =IF(Instructions!$C$6="","Coder ID not entered on Instructions sheet","Coder ID: "&Instructions!$C$6)
A4: Division | B4: Title | C4: Occupations | D4: Complete | E4: Add evidence | F4: Incomplete | G4: Not started | H4: % complete
A5: 1 | B5: Managers | C5: =COUNTIF(Coding!$AD$3:$AD$3452,A5) | D5: =COUNTIFS(Coding!$AD$3:$AD$3452,A5,Coding!$Y$3:$Y$3452,"Complete") | E5: =COUNTIFS(Coding!$AD$3:$AD$3452,A5,Coding!$Y$3:$Y$3452,"Add evidence") | F5: =COUNTIFS(Coding!$AD$3:$AD$3452,A5,Coding!$Y$3:$Y$3452,"Incomplete") | G5: =COUNTIFS(Coding!$AD$3:$AD$3452,A5,Coding!$Y$3:$Y$3452,"Not started") | H5: =IF(C5=0,0,D5/C5)
A6: 2 | B6: Professionals | C6: =COUNTIF(Coding!$AD$3:$AD$3452,A6) | D6: =COUNTIFS(Coding!$AD$3:$AD$3452,A6,Coding!$Y$3:$Y$3452,"Complete") | E6: =COUNTIFS(Coding!$AD$3:$AD$3452,A6,Coding!$Y$3:$Y$3452,"Add evidence") | F6: =COUNTIFS(Coding!$AD$3:$AD$3452,A6,Coding!$Y$3:$Y$3452,"Incomplete") | G6: =COUNTIFS(Coding!$AD$3:$AD$3452,A6,Coding!$Y$3:$Y$3452,"Not started") | H6: =IF(C6=0,0,D6/C6)
A7: 3 | B7: Technicians and Associate Professionals | C7: =COUNTIF(Coding!$AD$3:$AD$3452,A7) | D7: =COUNTIFS(Coding!$AD$3:$AD$3452,A7,Coding!$Y$3:$Y$3452,"Complete") | E7: =COUNTIFS(Coding!$AD$3:$AD$3452,A7,Coding!$Y$3:$Y$3452,"Add evidence") | F7: =COUNTIFS(Coding!$AD$3:$AD$3452,A7,Coding!$Y$3:$Y$3452,"Incomplete") | G7: =COUNTIFS(Coding!$AD$3:$AD$3452,A7,Coding!$Y$3:$Y$3452,"Not started") | H7: =IF(C7=0,0,D7/C7)
A8: 4 | B8: Clerks/Clerical Support Workers | C8: =COUNTIF(Coding!$AD$3:$AD$3452,A8) | D8: =COUNTIFS(Coding!$AD$3:$AD$3452,A8,Coding!$Y$3:$Y$3452,"Complete") | E8: =COUNTIFS(Coding!$AD$3:$AD$3452,A8,Coding!$Y$3:$Y$3452,"Add evidence") | F8: =COUNTIFS(Coding!$AD$3:$AD$3452,A8,Coding!$Y$3:$Y$3452,"Incomplete") | G8: =COUNTIFS(Coding!$AD$3:$AD$3452,A8,Coding!$Y$3:$Y$3452,"Not started") | H8: =IF(C8=0,0,D8/C8)
A9: 5 | B9: Service and Sales Workers | C9: =COUNTIF(Coding!$AD$3:$AD$3452,A9) | D9: =COUNTIFS(Coding!$AD$3:$AD$3452,A9,Coding!$Y$3:$Y$3452,"Complete") | E9: =COUNTIFS(Coding!$AD$3:$AD$3452,A9,Coding!$Y$3:$Y$3452,"Add evidence") | F9: =COUNTIFS(Coding!$AD$3:$AD$3452,A9,Coding!$Y$3:$Y$3452,"Incomplete") | G9: =COUNTIFS(Coding!$AD$3:$AD$3452,A9,Coding!$Y$3:$Y$3452,"Not started") | H9: =IF(C9=0,0,D9/C9)
A10: 6 | B10: Skilled Agricultural, Forestry and Fishery Workers | C10: =COUNTIF(Coding!$AD$3:$AD$3452,A10) | D10: =COUNTIFS(Coding!$AD$3:$AD$3452,A10,Coding!$Y$3:$Y$3452,"Complete") | E10: =COUNTIFS(Coding!$AD$3:$AD$3452,A10,Coding!$Y$3:$Y$3452,"Add evidence") | F10: =COUNTIFS(Coding!$AD$3:$AD$3452,A10,Coding!$Y$3:$Y$3452,"Incomplete") | G10: =COUNTIFS(Coding!$AD$3:$AD$3452,A10,Coding!$Y$3:$Y$3452,"Not started") | H10: =IF(C10=0,0,D10/C10)
A11: 7 | B11: Craft and Related Trades Workers | C11: =COUNTIF(Coding!$AD$3:$AD$3452,A11) | D11: =COUNTIFS(Coding!$AD$3:$AD$3452,A11,Coding!$Y$3:$Y$3452,"Complete") | E11: =COUNTIFS(Coding!$AD$3:$AD$3452,A11,Coding!$Y$3:$Y$3452,"Add evidence") | F11: =COUNTIFS(Coding!$AD$3:$AD$3452,A11,Coding!$Y$3:$Y$3452,"Incomplete") | G11: =COUNTIFS(Coding!$AD$3:$AD$3452,A11,Coding!$Y$3:$Y$3452,"Not started") | H11: =IF(C11=0,0,D11/C11)
A12: 8 | B12: Plant and Machine Operators, and Assemblers | C12: =COUNTIF(Coding!$AD$3:$AD$3452,A12) | D12: =COUNTIFS(Coding!$AD$3:$AD$3452,A12,Coding!$Y$3:$Y$3452,"Complete") | E12: =COUNTIFS(Coding!$AD$3:$AD$3452,A12,Coding!$Y$3:$Y$3452,"Add evidence") | F12: =COUNTIFS(Coding!$AD$3:$AD$3452,A12,Coding!$Y$3:$Y$3452,"Incomplete") | G12: =COUNTIFS(Coding!$AD$3:$AD$3452,A12,Coding!$Y$3:$Y$3452,"Not started") | H12: =IF(C12=0,0,D12/C12)
A13: 9 | B13: Elementary Occupations | C13: =COUNTIF(Coding!$AD$3:$AD$3452,A13) | D13: =COUNTIFS(Coding!$AD$3:$AD$3452,A13,Coding!$Y$3:$Y$3452,"Complete") | E13: =COUNTIFS(Coding!$AD$3:$AD$3452,A13,Coding!$Y$3:$Y$3452,"Add evidence") | F13: =COUNTIFS(Coding!$AD$3:$AD$3452,A13,Coding!$Y$3:$Y$3452,"Incomplete") | G13: =COUNTIFS(Coding!$AD$3:$AD$3452,A13,Coding!$Y$3:$Y$3452,"Not started") | H13: =IF(C13=0,0,D13/C13)
B14: All divisions | C14: =SUM(C5:C13) | D14: =SUM(D5:D13) | E14: =SUM(E5:E13) | F14: =SUM(F5:F13) | G14: =SUM(G5:G13) | H14: =IF(C14=0,0,D14/C14)

Sheet Lists
A1: Yes | B1: 0 | C1: 1 | D1: 0 | E1: Core | F1: More
A2: Partly | B2: 1 | C2: 2 | D2: 1 | E2: Supporting | F2: Same
A3: No | B3: 2 | C3: 3 | D3: 2 | E3: Not relevant | F3: Less
B4: 3 | D4: 3
B5: 4 | D5: 4
D6: 5
D7: 6
D8: 7
D9: 8
D10: 9
D11: 10
